Workbook
Name Datenschnitt_Übernahme__in_S_4_geplant: #N/A

Sheet Z-Programme
A1: Z-Programm R/3 (insgesamt 654) | B1: vorhanden EQA | C1: Übernahme in S/4 geplant | D1: USR CALM | E1: Welle 1 | F1: Welle 2 | G1: Welle 3 ff | H1: Coding Zahlwege | I1: Klärung durch | J1: Beschreibung
A2: Z_CLEAN_EVTTAB | B2: Nein | C2: Nein | J2: Hilfsprogramm zur Bereinigung Inkonsistenzen in Jobtabelle BTCEVTJOB
A3: Z_IDOC_STATUS_SET | B3: Nein | C3: Ja | F3: Nein | G3: Ja | J3: Idoc Status auf erledigt setzen (nur BuKrs 1000)
A4: Z_INFO_PRICING_SERVICES_USER | B4: Nein | C4: Nein | J4: Z_INFO_PRICING_SERVICES_USER lt. SAP Hinweis 1786263
A5: Z_REPAIR_ADRNR_1 | B5: Nein | C5: Nein | J5: Reparatur der Adressinkonsistenz in Tabelle VBPA und KNA1
A6: Z_SAPMZSWA | B6: Nein | C6: Ja | F6: Nein | G6: Ja | J6: Programm SAPMZSWA - Batterieservice
A7: Z_SAPMZSWA_MENUE | B7: Nein | C7: Ja | F7: Nein | G7: Ja | J7: Menü Batterieservice
A8: Z_SAPMZSWAT | B8: Nein | C8: Ja | F8: Nein | G8: Ja | J8: Modulpool: Elektronisches Bezahlen SWA-Terminal (Straßenwacht)
A9: Z0SAP_12 | B9: Nein | C9: Nein | J9: Datendatei-View: Geplante Abschreibungen auf Anlagen
A10: ZAA_ANLAGENTR_COPY_LANGTEXT | B10: Nein | C10: Nein | J10: Anlagentransfer Langtexte kopieren
A11: ZAA_ANLAGENTRANSFER | B11: Nein | C11: Nein | J11: Anlagentransfer
A12: ZAA_CO_KONTIERUNG | B12: Nein | C12: Nein | J12: Änderung von Innenaufträgen/Kostenstellen in Anlagen
A13: ZAA_INVE01 | B13: Nein | C13: Nein | J13: Inventurliste nach Anlagennummern / Anlagentext
A14: ZAA_INVE06 | B14: Nein | C14: Nein | J14: Inventurliste nach Anlagennummern / Anlagentext
A15: ZAA_INVE07 | B15: Nein | C15: Nein | J15: Inventurliste nach Kostenrechnungsobjekten
A16: ZAA_MASS_DOWN | B16: Nein | C16: Nein | D16: DEV-002 | J16: Anlagenstamm Massenänderung: Download
A17: ZAA_MASS_UP | B17: Nein | C17: Nein | D17: DEV-002 | J17: Massenänderung Anlagenstamm: Upload CSV-Datei
A18: ZAA_RAHIST01 | B18: Nein | C18: Nein | J18: Anlagenhistorie
A19: ZAA_RAPOST2010 | B19: Nein | C19: Nein | J19: Buchen der Abschreibungen
A20: ZAA_STAMMDAT_ALV | B20: Nein | C20: Nein | D20: DEV-002 | J20: Stammdaten-Auswertung ALV-Liste ( mehrzeilig )
A21: ZACAC_DATA_TRANSFER | B21: Ja | C21: Ja | D21: DEV-150 | E21: Ja | J21: Übernahme von Debitoren-/Kreditorenrechnungen in die Accrual Engine
A22: ZACAC_DSITEMS | B22: Nein | C22: Nein | J22: Anzeigen von Abgrenzungsobjekten + kd.eigene Parameter
A23: ZBC_ADDR_CHECK | B23: Nein | C23: Nein | J23: Reparaturprogramm: Prüfen Debitoren auf fehlende Adresse-Einträge in Archivierung
A24: ZBC_AL_REORG_OUT | B24: Nein | C24: Ja | F24: Ja | G24: Nein | J24: Archivelink Reorganisation - Erstellen Löschdatei und Tabelle für's Löschen von Sätzen in den Verknüpfungstabellen
A25: ZBC_AL_REORG_RETURN | B25: Nein | C25: Ja | F25: Ja | G25: Nein | J25: Archivelink Reorganisation - Rückantwort NE-Databridge
A26: ZBC_AL_REORG_VTABS | B26: Nein | C26: Ja | F26: Ja | G26: Nein | J26: Archivelink Reorganisation - Pflege der Verknüpfungstabellen
A27: ZBC_ANONYM_ZQ1 | B27: Nein | C27: Ja | F27: Ja | G27: Nein | J27: Anonymisierungstool in Q Systemen
A28: ZBC_BDCLOG_ALV | B28: Nein | C28: Ja | F28: Ja | G28: Nein | J28: Archivierte BDC Mappenprotokolle anzeigen
A29: ZBC_BDCLOG_ARCHIVE | B29: Nein | C29: Ja | F29: Ja | G29: Nein | J29: BDC Mappenprotokolle archivieren
A30: ZBC_BDCLOG_ARCHIVE_FIX | B30: Nein | C30: Ja | F30: Ja | G30: Nein | J30: BDC Mappenprotokolle archiv Objekte importieren
A31: ZBC_BELEG_VOLUME | B31: Nein | C31: Nein | J31: Ermittlung von Beleganzahl / -wert je Buchungskreis als Basis für Verteilschlüssel SAP Systempreis Verteilung
A32: ZBC_CALL_PROCEDURE | B32: Nein | C32: Nein | J32: Aufruf einer "Stored Procedure" in der Berichtswesendatenbank
A33: ZBC_CHECK_NRIV | B33: Nein | C33: Ja | F33: Ja | G33: Nein | J33: mit diesem Programm können Nummernkreise auf Fehler geprüft werden und freie Intervalle ermittelt werden.
A34: ZBC_COPY_DATASET | B34: Nein | C34: Ja | F34: Ja | G34: Nein | J34: Wird benötigt für ELMO für Dateiaufstellung für Netz HG105C. Es ist eine Kopie von ZFI_COPY_TEXT_DATASET ergänzt mit Archivierungsfunktionalität
A35: ZBC_EVENT_RAISE | B35: Ja | C35: Ja | E35: Ja | J35: Auslösen eines Kundenereignisses
A36: ZBC_EXCELTABUPLOAD | B36: Nein | C36: Nein | J36: Generischer Upload von Excel-Tabellen in R/3-Tabellen
A37: ZBC_F110_JOBCTRL | B37: Nein | C37: Offen | F37: ? | G37: ? | I37: J. Schaut | J37: Zahllauf Folgeverarbeitungssteuerung
A38: ZBC_F110_SPOOL_UPDATE | B38: Nein | C38: Offen | F38: ? | G38: ? | I38: J. Schaut | J38: Update von Spool-Datasets (Zahllaufversion)
A39: ZBC_FILE_DELETE | B39: Ja | C39: Ja | E39: Ja | J39: Dateienlöschung über Report ZBC_FILE_DELETE
A40: ZBC_FILE_EVENT_RAISE | B40: Ja | C40: Ja | E40: Ja | J40: Dateieneventauslösung
A41: ZBC_GET_WORKLOAD_STATISTIC | B41: Nein | C41: Nein | J41: Download Workload Statistics
A42: ZBC_JOB_ABORT | B42: Ja | C42: Ja | E42: Ja | J42: Job Abbrechen wenn eine Liste best. String enthält
A43: ZBC_JOBCONTROL | B43: Nein | C43: Nein
A44: ZBC_LOEVM_DEBI_KREDI | B44: Nein | C44: Nein | J44: Programm zur Pflege der Löschvormerkung für Debitoren und Kreditoren
A45: ZBC_LOEVM_DEBI_KREDI_2 | B45: Nein | C45: Nein | J45: Setzen Löschvormerkung anhand Tage ohne Buchungen
A46: ZBC_LOGO_SWITCH | B46: Nein | C46: Nein | I46: P. Haisch | J46: Logo-Clicks ein/ausschalten -> gehört zu OREA
A47: ZBC_MAESTRO | B47: Nein | C47: Nein | J47: ZBC_MAESTRO
A48: ZBC_NACH_UPDATE_TESTSYSTEM | B48: Nein | C48: Ja | F48: Ja | G48: ? | I48: Basis | J48: Update Tabelle NACH im Test-System ("Sofort ausgeben", "Ausgabegerät")
A49: ZBC_NOTFALLUSERAKTIEVIERUNG | B49: Nein | C49: Nein | J49: Programm zur automatischen Userinaktivierung
A50: ZBC_OREA_COA | B50: Ja | C50: Ja | D50: DEV-105 | E50: Ja | J50: Füllen der COA-Tabellen
A51: ZBC_OREA_COA_NACHVERARBEITUNG | B51: Ja | C51: Ja | E51: Ja | J51: Nachverarbeitung der Freigabehierarchie
A52: ZBC_OREA_COA_TEST | B52: Nein | C52: Nein | I52: P. Haisch | J52: Testutils -> OREA
A53: ZBC_OREA_COA_USER_LOESCHEN | B53: Nein | C53: Offen | F53: ? | G53: ? | I53: A. Gaida / R. Schildberger | J53: Löschen von einzelnen Usern aus der COA
A54: ZBC_OREA_FREIGEBER_TEST | B54: Nein | C54: Ja | D54: DEV-105 | E54: Ja | J54: Test des Freigeberfunktionsbausteins
A55: ZBC_SET_TVARVC | B55: Ja | C55: Ja | E55: Ja | J55: Parameter in TVARVC belegen und updaten
A56: ZBC_SPERR_STAMM_DS | B56: Nein | C56: Nein | J56: Datenschutz: Pflege Berechtigungsgruppe im Stammsatz
A57: ZBC_SPOOL_ARCHIV | B57: Ja | C57: Ja | E57: Ja | J57: Drucklistenarchivierung
A58: ZBC_SPOOL_OUTPUT | B58: Ja | C58: Ja | E58: Ja | J58: Zusätzliches Ausgeben / Senden von Spoollisten
A59: ZBC_SPOOL_PCOUNT | B59: Nein | C59: Ja | F59: Ja | G59: Nein | J59: Ermittlung Seitenanzahl und Ausgabe von Spool-Datasets
A60: ZBC_ST03N | B60: Nein | C60: Nein | J60: Auswertung Systemlast
A61: ZBC_TAB_EXPIMP | B61: Ja | C61: Ja | E61: Ja | J61: ZBC_TAB_EXPIMP Tabellen Exportieren/Importieren
A62: ZBC_TABELLEN_TRANSFER | B62: Nein | C62: Nein | J62: Programm ZBC_TABELLEN_TRANSFER
A63: ZBC_USERINAKTIVIERUNG | B63: Nein | C63: Ja | D63: DEV-084 | E63: Ja | J63: Programm zur automatischen Userinaktivierung
A64: ZBC_VARIANT_LIST | B64: Nein | C64: Ja | F64: Ja | G64: Nein | J64: Reportvarianten-Scanfunktionalität
A65: ZBC_VARIANT_LIST_ALV | B65: Nein | C65: Ja | F65: Ja | G65: Nein | J65: Reportvarianten-Scanfunktionalität
A66: ZBC_ZEMAREP_FRGREORG | B66: Nein | C66: Ja | D66: DEV-084 | E66: Ja | J66: Reorg Tabelle ZBC_ZEMAREP_FRG
A67: ZBC_ZEMAREP_GET | B67: Ja | C67: Ja | D67: DEV-084 | E67: Ja | J67: lesen zemarep
A68: ZBC_ZEMAREP_USER | B68: Ja | C68: Ja | D68: DEV-084 | E68: Ja | J68: ZEMAREP User-Pflege
A69: ZBC_ZEMAREP_USERCHG_REO | B69: Ja | C69: Ja | E69: Ja | J69: Anzeige/Löschen Tabelle ZREP_USERCHG
A70: ZBC_ZEMAREP_USRGUELT | B70: Nein | C70: Ja | D70: DEV-084 | E70: Ja | J70: user gültigkeit prüfen
A71: ZBC_ZRSLG_SERVERS_1692951 | B71: Nein | C71: Nein | J71: Korrekturprogramm Upgrade SNOTE 2164430
A72: ZBC_ZRUTDDLSLDEL_2163340 | B72: Nein | C72: Nein | J72: Korrekturprogramm Upgrade SNOTE 2164430
A73: ZCA_MAIL2 | B73: Nein | C73: Nein | J73: Globale Routinen Luftrettung
A74: ZCA_MAPPCHECK | B74: Ja | C74: Ja | E74: Ja | J74: Mappenstatus
A75: ZCA_TEST_GOS | B75: Nein | C75: Nein | J75: Testprogramm
A76: ZCA_WARTEN | B76: Ja | C76: Ja | E76: Ja | J76: Warten n Minuten (max. 30)
A77: ZCMFIFU1 | B77: Nein | C77: Nein | J77: OSS: 156239 Report Datenaufbau Banksalden
A78: ZCO_ABSTIMMUNG | B78: Nein | C78: Nein | J78: Abstimmung Intercompany
A79: ZCO_ABSTIMMUNG_ARCHIVLINK | B79: Nein | C79: Nein | J79: FI: Archiv_Link_Rechnungsbeleg: FI-Rechnungsdruck
A80: ZCO_ABSTIMMUNG_PRUEFUNG | B80: Nein | C80: Nein | J80: Prüfung der CO/FI-Abstimmung
A81: ZCO_ABZUG_KSTPROJEKT_UMSETZUNG | B81: Nein | C81: Nein | D81: DEV-109 | J81: Programm ZCO_ABZUG_KSTPROJEKT_UMSETZUNG
A82: ZCO_AVM_DATENABZUG | B82: Nein | C82: Nein | D82: DEV-110 | J82: Kostenarten- / Profitcenter-Datenabzug
A83: ZCO_BEWEGUNGSDATEN_ERGRE | B83: Nein | C83: Nein | J83: Initialization und At Selection Screen
A84: ZCO_DATENABZUG_PCA | B84: Nein | C84: Nein
A85: ZCO_DRUCKER_SPOOL | B85: Nein | C85: Nein | D85: DEV-111
A86: ZCO_ERGEBNISRECHNUNG | B86: Nein | C86: Nein | J86: Datenabzug Controlling für die Ergebnisrechnung
A87: ZCO_HIERARCHIEPRUEFUNG | B87: Nein | C87: Nein | J87: Programm ZCO_HIERARCHIEPRUEFUNG
A88: ZCO_IA_ABRECHNUNGSSCHEMA | B88: Nein | C88: Nein | J88: Abrechnungsschema in vorhandenen Aufträgen aktualisieren
A89: ZCO_ILV_AUSWERT | B89: Nein | C89: Nein | J89: Abstimmung SAPCO mit Sachkonten ILV aus SAP-FI
A90: ZCO_ILV_AUTOMABHAK | B90: Nein | C90: Nein | J90: Programm ZCO_ILV_AUTOMABHAK
A91: ZCO_ILV_FI | B91: Nein | C91: Nein | J91: Auswertung FI-Buchungen für ILV
A92: ZCO_ILV_KENNZAHL | B92: Nein | C92: Nein | J92: Programm ZCO_ILV_KENNZAHLEN
A93: ZCO_ILV_KONVERT | B93: Nein | C93: Nein | J93: Konvertierung ILV-Schnittstelle: Alte -> Neue Struktur
A94: ZCO_ILV_LIZENZVERRECHNUNG | B94: Nein | C94: Nein
A95: ZCO_ILV_PCDATEIUEBERNAHME | B95: Nein | C95: Nein | J95: Übernahme der Dateien für die ILV
A96: ZCO_ILV_POSTPROT_AKT | B96: Nein | C96: Nein | J96: Buchungsprotokolltabelle aktualisieren
A97: ZCO_ILV_SAMMLER_LOESCHEN | B97: Nein | C97: Nein | J97: Sammeldateiloeschung
A98: ZCO_ILV_STS | B98: Nein | C98: Nein | J98: Programm ZCO_ILV
A99: ZCO_ILV_VORPROGRAMM | B99: Nein | C99: Nein | J99: Vorprogramm zur ILV
A100: ZCO_KALC_DRUCK | B100: Nein | C100: Nein | J100: KALC FI Belegdaten für den Druck exportieren
...

Sheet Tabelle3

Sheet Zuordnung Z-Programme zu DEVs
A1: Z-Programm in DEV für S/4 | B1: USR | C1: Welle 2 und 3 | D1: vorhanden in R/3 | E1: gesperrt | F1: Schnitt- stellen- programm | G1: Thema
A2: ZMM_MATREORG | B2: DEV-006 | D2: x | G2: Lagerver- und Materialverwaltung
A3: ZMM_MM60 | B3: DEV-006 | D3: x | G3: Lagerver- und Materialverwaltung
A4: ZMM_MM00 | B4: DEV-006 | D4: x | G4: Lagerver- und Materialverwaltung
A5: ZMM_MM01 | B5: DEV-006 | D5: x | G5: Lagerver- und Materialverwaltung
A6: ZMM_LAPS10 | B6: DEV-009 | D6: x | G6: Lagerplatzverwaltung
A7: ZMM_LAPS20 | B7: DEV-009 | D7: x | F7: x | G7: Lagerplatzverwaltung
A8: ZMM_LAPS30 | B8: DEV-009 | D8: x | G8: Lagerplatzverwaltung
A9: ZMM_LAPS40 | B9: DEV-009 | D9: x | F9: x | G9: Lagerplatzverwaltung
A10: ZMM_LAPS45 | B10: DEV-009 | D10: x | F10: x | G10: Lagerplatzverwaltung
A11: ZMM_LAPS52 | B11: DEV-009 | D11: x | G11: Lagerplatzverwaltung
A12: ZMM_LAPS70 | B12: DEV-009 | D12: x | F12: x | G12: Lagerplatzverwaltung
A13: ZMM_LAPS73 | B13: DEV-009 | D13: x | F13: x | G13: Lagerplatzverwaltung
A14: ZMM_LAPS75 | B14: DEV-009 | D14: x | G14: Lagerplatzverwaltung
A15: ZMM_LAPSDR | B15: DEV-009 | D15: x | F15: x | G15: Lagerplatzverwaltung
A16: ZMM_LPS | B16: DEV-009 | F16: x | G16: Lagerplatzverwaltung
A17: ZMM_INV | B17: DEV-010 | D17: x | G17: Inventurunterstützung
A18: ZMM_MI04 | B18: DEV-010 | D18: x | G18: Inventurunterstützung
A19: ZMM_INVDIF | B19: DEV-010 | D19: x | G19: Inventurunterstützung
A20: ZMM_MI31 | B20: DEV-010 | D20: x | G20: Inventurunterstützung
A21: ZMM_MI03 | B21: DEV-010 | G21: Inventurunterstützung
A22: ZFI_PAYMENT_AVIS | B22: DEV-012 | E22: x
A23: ALL-G08 | B23: DEV-021
A24: zsd_nast_archiv | B24: DEV-025 | D24: x
A25: ZFI_AVM_Upload_AUFNR_KFZ | B25: DEV-033 | D25: x | E25: x | F25: x | G25: MBC
A26: ZFI_AVM_Versicherung | B26: DEV-033 | D26: x | E26: x | G26: MBC
A27: ZFI_Mahns_Loesch | B27: DEV-034 | D27: x | E27: x | G27: Dispute Management
A28: ZFI_Mahns_Mahnv | B28: DEV-034 | D28: x | E28: x | G28: Dispute Management
A29: ZFI_MAHNSTOPP | B29: DEV-034 | D29: x | E29: x | G29: Dispute Management
A30: ZFI_MAHNSTOPP_ABZUG | B30: DEV-034 | D30: x | E30: x | G30: Dispute Management
A31: ZFI_Mahnstopp_Setzen | B31: DEV-034 | D31: x | E31: x | G31: Dispute Management
A32: ZFI_Mahnstopp2 | B32: DEV-034 | D32: x | E32: x | G32: Dispute Management
A33: ZFI_Mahnvorschlag | B33: DEV-035 | D33: x | E33: x | G33: Dispute Management
A34: ZFI_CCS_Auswert | B34: DEV-037 | D34: x | E34: x | G34: Dispute Management
A35: ZFI_CCS_Drucke | B35: DEV-037 | D35: x | E35: x | G35: Dispute Management
A36: ZFI_Druck_Container | B36: DEV-037 | D36: x | E36: x | G36: Dispute Management
A37: ZFI_Spool_Update | B37: DEV-037 | D37: x | E37: x | G37: Dispute Management
A38: ZFI_Inko_Cockpit | B38: DEV-038 | D38: x | E38: x | F38: x | G38: Dispute Management
A39: ZFI_Inko_Cockpit_Korrektur | B39: DEV-038 | D39: x | E39: x | F39: x | G39: Dispute Management
A40: ZFI_Rate01 | B40: DEV-038 | D40: x | E40: x | F40: x | G40: Dispute Management
A41: ZFI_Raten_Rueck01 | B41: DEV-038 | D41: x | E41: x | F41: x | G41: Dispute Management
A42: ZFI_Raten_Uebergabe | B42: DEV-038 | D42: x | E42: x | F42: x | G42: Dispute Management
A43: ZFI_INKASSO_EOS | B43: DEV-038 | D43: x | E43: x | F43: x | G43: Dispute Management
A44: ZFI_INKO_ZAHLUNG_EOS | B44: DEV-038 | D44: x | E44: x | F44: x | G44: Dispute Management
A45: ZFI_Inko_Zahlung | B45: DEV-039 | D45: x | E45: x | F45: x | G45: Dispute Management
A46: ZFI_Inkasso | B46: DEV-040 | D46: x | E46: x | F46: x | G46: Dispute Management
A47: ZFI_Inko00 | B47: DEV-041 | D47: x | E47: x | F47: x | G47: Dispute Management
A48: ZFI_Inko03 | B48: DEV-041 | D48: x | E48: x | F48: x | G48: Dispute Management
A49: ZFI_Inko04 | B49: DEV-041 | D49: x | E49: x | F49: x | G49: Dispute Management
... A57: ZFI_INKO_COCKPI2 | B57: DEV-041 | D57: x | E57: x | F57: x | G57: Dispute Management
A58: ZMM_MAR1_AENDBELG | B58: DEV-053 | D58: x | G58: MAR
A59: ZMM_MAR1_BESTAND_HISTORY | B59: DEV-053 | D59: x | G59: MAR
A60: ZCL_MAR_EVENT | B60: DEV-053 | G60: MAR
A61: ZCL_MAR_KUNDE | B61: DEV-053 | G61: MAR
A62: ZCL_MAR_NACHRICHTENART | B62: DEV-053 | G62: MAR
A63: ZCL_MAR_NAST_STATUS | B63: DEV-053 | G63: MAR
A64: ZCL_MAR_RECHNUNGSTYP | B64: DEV-053 | G64: MAR
A65: ZSD_MAR_ADMIN | B65: DEV-053 | D65: x | G65: MAR
A66: ZSD_MAR_BASIS | B66: DEV-053 | D66: x | G66: MAR
A67: ZSD_MAR_BELEGHIS | B67: DEV-053 | D67: x | G67: MAR
A68: ZSD_MAR_DRUCK | B68: DEV-053 | D68: x | G68: MAR
A69: ZSD_MAR_FI | B69: DEV-053 | D69: x | G69: MAR
A70: ZSD_MAR_IMPORT | B70: DEV-053 | D70: x | G70: MAR
A71: ZSD_MAR_RECH_EMAIL_SEND | B71: DEV-053 | D71: x | G71: MAR
A72: ZSD_MAR_USR_STAT | B72: DEV-053 | D72: x | G72: MAR
A73: ZSD_MARM | B73: DEV-053 | D73: x | G73: MAR
A74: ZSD_MARV | B74: DEV-053 | D74: x | G74: MAR
A75: ZSD_NAST_MAR | B75: DEV-053 | D75: x | G75: MAR
A76: ZFI_BARCO_DEL | B76: DEV-064 | D76: x | G76: Archivierung
... A82: ZFI_BARCO_ZUO | B82: DEV-064 | D82: x | G82: Archivierung
A83: ZFI_ELFE03 | B83: DEV-067 | D83: x | F83: x | G83: Telekom
A84: ZFI_ELMO | B84: DEV-067 | D84: x | F84: x | G84: Telekom
A85: ZFI_ELSY_SCHNITTSTELLE | B85: DEV-067 | D85: x | F85: x | G85: Telekom
A86: ZSD_AUFRUE | B86: DEV-068 | D86: x
A87: ZMM_LAGV | B87: DEV-070 | D87: x
A88: ZMM_MAT_AENDERUNGEN | B88: DEV-070 | D88: x
A89: ZFI_LZBKZ_BELEGE_CHECK | B89: DEV-071 | D89: x | G89: LZB Kennz.
A90: ZFI_CUSTOMER_ADD_DATA | B90: DEV-071 | G90: LZB Kennz.
A91: ZFI_CUST_ADD_DAT_CS | B91: DEV-071 | G91: LZB Kennz.
A92: ZFI_CUST_ADD_DAT_BI | B92: DEV-071 | G92: LZB Kennz.
A93: ZFI_VENDOR_ADD_DATA | B93: DEV-071 | G93: LZB Kennz.
A94: ZFI_VEND_ADD_DATA_CS | B94: DEV-071 | G94: LZB Kennz.
A95: ZFI_VEND_ADD_DATA_BI | B95: DEV-071 | G95: LZB Kennz.
A96: ZFI_FI_LZBKZ_LANDL_DERIVE | B96: DEV-071 | G96: LZB Kennz.
A97: ZFI_FILE_FOR_ABSTIMMTOOL | B97: DEV-072 | D97: x | F97: x | G97: AVM
A98: ZFI_AVMBROKER_ABSTIMM_SUPP | B98: DEV-072 | D98: x | F98: x | G98: AVM
A99: ZFI_AVMBR02 | B99: DEV-072 | D99: x | F99: x | G99: AVM
A100: ZFI_AVMBR04 | B100: DEV-072 | D100: x | F100: x | G100: AVM
A101: ZFI_AVM_UMBUCHUNG | B101: DEV-072 | D101: x | F101: x | G101: AVM
A102: ZFI_AVMBR01 | B102: DEV-072 | D102: x | F102: x | G102: AVM
A103: ZFI_ANZ_REISE_PBS | B103: DEV-073 | D103: x | F103: x | G103: concur
A104: ZSD_SHOEXP | B104: DEV-079 | D104: x | F104: x | G104: SD-Shop
A105: ZSD_SHOEXPSTA | B105: DEV-079 | D105: x | F105: x | G105: SD-Shop
A106: ZSD_SHOSTA2 | B106: DEV-079 | D106: x | F106: x | G106: SD-Shop
A107: ZSD_SHOKUN_MM | B107: DEV-079 | D107: x | F107: x | G107: SD-Shop
A108: ZSD_SHOP_STAT | B108: DEV-079 | D108: x | F108: x | G108: SD-Shop
A109: zsd_shoimp | B109: DEV-079 | D109: x | F109: x | G109: SD-Shop
A110: ZFI_AVM_AOBJD | B110: DEV-080 | D110: x | G110: Archivierung
A111: ZFI_AVM_AOBJD | B111: DEV-080 | D111: x | G111: Archivierung
A112: ZFI_AVM_AOBJR | B112: DEV-080 | D112: x | G112: Archivierung
...

Sheet ZProgramm-ZTransaktion - KOMPLE
A1: Programmname | B1: In meiner Liste? | C1: Beschreibung | D1: Programmtyp | E1: Für Welle 1 relevant? | F1: End-to-End-Prozess? | G1: 1. Schritt: Gap aus der Ramp-Up-Phase: Entsprechende Gaps durch das KDB freigegeben. | H1: 1. Schritt: - Nachjustierung: Entscheidung in Explorephase, Gap trotz Freigabe nicht zu übernehmen: | I1: Änderungen der Gaps/ Z-Artefakte nach Ramp-Up-Phase, die aber zu berücksichtigen sind. | J1: 2. Schritt: Z-Artefakte in Explorephase mit ADAC IT besprochen - über X - filtern: bisher keine Freigabe durch KDB | K1: 2. Schritt: Empfehlung zur Übernahme: Ja, Nein, tbd, nicht geklärt | L1: 2. Schritt: Kommentare zu den Z-Artefakten, die nicht in der Ramp-Up-Phase durch das KDB freigegeben wurden. | M1: Zuordnung zu den Userstorys bei Relevanz für Welle 1 | N1: Datei | O1: Freigabe (Filter auf ja) über KDB, da in Gapliste aus Ramp-Up-Phase enthalten | P1: Status für Übernahme nicht über Gapliste, sondern aus Beurteilung der Transaktionen in Z-Artefaktenliste von Johannes und Volker | Q1: vorherige Bewertung Übernahme
A2: Z_CLEAN_EVTTAB | B2: =VLOOKUP(A2,'Z-Programme'!$A$2:$A$650,1,FALSE) -> Z_CLEAN_EVTTAB | C2: Hilfsprogramm zur Bereinigung Inkonsistenzen in Jobtabelle BTCEVTJOB | D2: 1 Ausführbares Programm | E2: Grundsätzlich Nein: für keine Welle relevant | F2: Utitilites/SAP Supportpackage | J2: X | K2: Nein, keine Übernahme | L2: Roland, 27.5.2024: Nein, nicht übernehmen, mit Johannes geklärt. | N2: =IF(#REF!="Ja",VLOOKUP(A2,'[1]ZArtefakte aus Listen'!A:B,2,0),"") -> #REF! | Q2: =IF(#REF!="Ja",VLOOKUP(A2,'[1]ZArtefakte aus Listen'!A:D,4,0),"") -> #REF!
A3: Z_IDOC_STATUS_SET | B3: =VLOOKUP(A3,'Z-Programme'!$A$2:$A$650,1,FALSE) -> Z_IDOC_STATUS_SET | C3: Idoc Status auf erledigt setzen | D3: 1 Ausführbares Programm | E3: Ja, Übernahme, aber nicht relevant für Welle 1 | F3: I2C - Utilites Warenwirtschaft ETM | J3: X | K3: Ja, Übernahme | L3: Roland, 27.5.204: Ja, wird benötigt, aber nicht in Welle 1; geklärt mit J. Schaut und V. Niemann | N3: =IF(#REF!="Ja",VLOOKUP(A3,'[1]ZArtefakte aus Listen'!A:B,2,0),"") -> #REF! | Q3: =IF(#REF!="Ja",VLOOKUP(A3,'[1]ZArtefakte aus Listen'!A:D,4,0),"") -> #REF!
A4: Z_INFO_PRICING_SERVICES_USER | B4: =VLOOKUP(A4,'Z-Programme'!$A$2:$A$650,1,FALSE) -> Z_INFO_PRICING_SERVICES_USER | C4: Z_INFO_PRICING_SERVICES_USER lt. SAP Hinweis 1786263 | D4: 1 Ausführbares Programm | E4: Grundsätzlich Nein: für keine Welle relevant | F4: Irrelevant | J4: X | K4: Nein, keine Übernahme | L4: Roland, 15.11.2023: Nein, bezieht sich auf einen Hinweis aus 2018. | N4: =IF(#REF!="Ja",VLOOKUP(A4,'[1]ZArtefakte aus Listen'!A:B,2,0),"") -> #REF! | Q4: =IF(#REF!="Ja",VLOOKUP(A4,'[1]ZArtefakte aus Listen'!A:D,4,0),"") -> #REF!
A5: Z_REPAIR_ADRNR_1 | B5: =VLOOKUP(A5,'Z-Programme'!$A$2:$A$650,1,FALSE) -> Z_REPAIR_ADRNR_1 | C5: Reparatur der Adressinkonsistenz in Tabelle VBPA und KNA1 | D5: 1 Ausführbares Programm | E5: Grundsätzlich Nein: für keine Welle relevant | F5: Irrelevant | J5: X | K5: Nein, keine Übernahme | L5: Kilian, 15.11.2023: Nein, müsste oboselt sein, auch wegen neues BP-Ansatz. | N5: =IF(#REF!="Ja",VLOOKUP(A5,'[1]ZArtefakte aus Listen'!A:B,2,0),"") -> #REF! | Q5: =IF(#REF!="Ja",VLOOKUP(A5,'[1]ZArtefakte aus Listen'!A:D,4,0),"") -> #REF!
A6: Z_SAPMZSWA | B6: =VLOOKUP(A6,'Z-Programme'!$A$2:$A$650,1,FALSE) -> Z_SAPMZSWA | C6: Programm SAPMZSWA | D6: M Modulpool | E6: Ja, Übernahme, aber nicht relevant für Welle 1 | F6: I2C | J6: X | K6: Ja, Übernahme | L6: Roland, 27.5.204: Ja, wird benötigt, aber nicht in Welle 1; geklärt mit J. Schaut und V. Niemann | N6: =IF(#REF!="Ja",VLOOKUP(A6,'[1]ZArtefakte aus Listen'!A:B,2,0),"") -> #REF! | Q6: =IF(#REF!="Ja",VLOOKUP(A6,'[1]ZArtefakte aus Listen'!A:D,4,0),"") -> #REF!
A7: Z_SAPMZSWA_MENUE | B7: =VLOOKUP(A7,'Z-Programme'!$A$2:$A$650,1,FALSE) -> Z_SAPMZSWA_MENUE | C7: Menü Batterieservice | D7: M Modulpool | E7: Ja, Übernahme, aber nicht relevant für Welle 1 | F7: I2C | J7: X | K7: Ja, Übernahme | L7: Roland, 27.5.204: Ja, wird benötigt, aber nicht in Welle 1; geklärt mit J. Schaut und V. Niemann | N7: =IF(#REF!="Ja",VLOOKUP(A7,'[1]ZArtefakte aus Listen'!A:B,2,0),"") -> #REF! | Q7: =IF(#REF!="Ja",VLOOKUP(A7,'[1]ZArtefakte aus Listen'!A:D,4,0),"") -> #REF!
A8: Z_SAPMZSWAT | B8: =VLOOKUP(A8,'Z-Programme'!$A$2:$A$650,1,FALSE) -> Z_SAPMZSWAT | C8: Modulpool: Elektronisches Bezahlen SWA-Terminal | D8: M Modulpool | E8: Ja, Übernahme, aber nicht relevant für Welle 1 | F8: I2C | J8: X | K8: Ja, Übernahme | L8: Roland, 27.5.204: Ja, wird benötigt, aber nicht in Welle 1; geklärt mit J. Schaut und V. Niemann | N8: =IF(#REF!="Ja",VLOOKUP(A8,'[1]ZArtefakte aus Listen'!A:B,2,0),"") -> #REF! | Q8: =IF(#REF!="Ja",VLOOKUP(A8,'[1]ZArtefakte aus Listen'!A:D,4,0),"") -> #REF!
A9: Z0SAP_12 | B9: =VLOOKUP(A9,'Z-Programme'!$A$2:$A$650,1,FALSE) -> Z0SAP_12 | C9: Datendatei-View: Geplante Abschreibungen auf Anlagen | D9: 1 Ausführbares Programm | E9: Grundsätzlich Nein: für keine Welle relevant | F9: A2R - Utitlities Anlagenmanagement | K9: Nein, keine Übernahme | L9: Roland, 12.6.2024: Info von Johannes Schaut per Mail. Nicht relevant für keine Welle | M9: X | N9: =IF(#REF!="Ja",VLOOKUP(A9,'[1]ZArtefakte aus Listen'!A:B,2,0),"") -> #REF! | Q9: =IF(#REF!="Ja",VLOOKUP(A9,'[1]ZArtefakte aus Listen'!A:D,4,0),"") -> #REF!
A10: ZAA_ANLAGENTR_COPY_LANGTEXT | B10: =VLOOKUP(A10,'Z-Programme'!$A$2:$A$650,1,FALSE) -> ZAA_ANLAGENTR_COPY_LANGTEXT | C10: Anlagentransfer Langtexte kopieren | D10: 1 Ausführbares Programm | E10: Grundsätzlich Nein: für keine Welle relevant | F10: Irrelevant | J10: X | K10: Nein, keine Übernahme | L10: Roland, 15.11.2023: Nein, Rückführung auf den SAP Standard gemäß Projektvorgabe. | N10: =IF(#REF!="Ja",VLOOKUP(A10,'[1]ZArtefakte aus Listen'!A:B,2,0),"") -> #REF! | Q10: =IF(#REF!="Ja",VLOOKUP(A10,'[1]ZArtefakte aus Listen'!A:D,4,0),"") -> #REF!
A11: ZAA_ANLAGENTRANSFER | B11: =VLOOKUP(A11,'Z-Programme'!$A$2:$A$650,1,FALSE) -> ZAA_ANLAGENTRANSFER | C11: Anlagentransfer | D11: 1 Ausführbares Programm | E11: Grundsätzlich Nein: für keine Welle relevant | F11: Irrelevant | J11: X | K11: Nein, keine Übernahme | L11: Roland, 15.11.2023: Nein, Rückführung auf den SAP Standard gemäß Projektvorgabe. | N11: =IF(#REF!="Ja",VLOOKUP(A11,'[1]ZArtefakte aus Listen'!A:B,2,0),"") -> #REF! | Q11: =IF(#REF!="Ja",VLOOKUP(A11,'[1]ZArtefakte aus Listen'!A:D,4,0),"") -> #REF!
A12: ZAA_CO_KONTIERUNG | B12: =VLOOKUP(A12,'Z-Programme'!$A$2:$A$650,1,FALSE) -> ZAA_CO_KONTIERUNG | C12: Änderung von Innenaufträgen/Kostenstellen in Anlagen | D12: 1 Ausführbares Programm | E12: Grundsätzlich Nein: für keine Welle relevant | F12: Irrelevant | J12: X | K12: Nein, keine Übernahme | L12: Roland, 15.11.2023: Nein, Rückführung auf den SAP Standard gemäß Projektvorgabe. | N12: =IF(#REF!="Ja",VLOOKUP(A12,'[1]ZArtefakte aus Listen'!A:B,2,0),"") -> #REF! | Q12: =IF(#REF!="Ja",VLOOKUP(A12,'[1]ZArtefakte aus Listen'!A:D,4,0),"") -> #REF!
A13: ZAA_INVE01 | B13: =VLOOKUP(A13,'Z-Programme'!$A$2:$A$650,1,FALSE) -> ZAA_INVE01 | C13: Inventurliste nach Anlagennummern / Anlagentext | D13: 1 Ausführbares Programm | E13: Grundsätzlich Nein: für keine Welle relevant | F13: Irrelevant | J13: X | K13: Nein, keine Übernahme | L13: Roland, 15.11.2023: Nein, Rückführung auf den SAP Standard gemäß Projektvorgabe. | N13: =IF(#REF!="Ja",VLOOKUP(A13,'[1]ZArtefakte aus Listen'!A:B,2,0),"") -> #REF! | Q13: =IF(#REF!="Ja",VLOOKUP(A13,'[1]ZArtefakte aus Listen'!A:D,4,0),"") -> #REF!
A14: ZAA_INVE06 | B14: =VLOOKUP(A14,'Z-Programme'!$A$2:$A$650,1,FALSE) -> ZAA_INVE06 | C14: Inventurliste nach Anlagennummern / Anlagentext | D14: 1 Ausführbares Programm | E14: Grundsätzlich Nein: für keine Welle relevant | F14: Irrelevant | J14: X | K14: Nein, keine Übernahme | L14: Roland, 15.11.2023: Nein, Rückführung auf den SAP Standard gemäß Projektvorgabe. | N14: =IF(#REF!="Ja",VLOOKUP(A14,'[1]ZArtefakte aus Listen'!A:B,2,0),"") -> #REF! | Q14: =IF(#REF!="Ja",VLOOKUP(A14,'[1]ZArtefakte aus Listen'!A:D,4,0),"") -> #REF!
A15: ZAA_INVE07 | B15: =VLOOKUP(A15,'Z-Programme'!$A$2:$A$650,1,FALSE) -> ZAA_INVE07 | C15: Inventurliste nach Kostenrechnungsobjekten | D15: 1 Ausführbares Programm | E15: Grundsätzlich Nein: für keine Welle relevant | F15: Irrelevant | J15: X | K15: Nein, keine Übernahme | L15: Roland, 15.11.2023: Nein, Rückführung auf den SAP Standard gemäß Projektvorgabe. | N15: =IF(#REF!="Ja",VLOOKUP(A15,'[1]ZArtefakte aus Listen'!A:B,2,0),"") -> #REF! | Q15: =IF(#REF!="Ja",VLOOKUP(A15,'[1]ZArtefakte aus Listen'!A:D,4,0),"") -> #REF!
A16: ZAA_MASS_DOWN | B16: =VLOOKUP(A16,'Z-Programme'!$A$2:$A$650,1,FALSE) -> ZAA_MASS_DOWN | C16: Anlagenstamm Massenänderung: Download | D16: 1 Ausführbares Programm | E16: Grundsätzlich Nein: für keine Welle relevant | F16: Irrelevant | G16: Finance Gapliste: Gap 01-(A2R-03.06) | H16: Nein, keine Übernahme: Abstimmung mit NTT und Fr. Brahms am 12.3.2024 | I16: Ursprünglich freigegeben im KDB, wird aber nicht mehr benötigt. | K16: Nein, keine Übernahme | L16: Roland, 9.7.2024: Nachträgliche Änderung zum KDB-Beschluss, da Z-Artefakte als obsolet angesehen werden. | N16: =IF(#REF!="Ja",VLOOKUP(A16,'[1]ZArtefakte aus Listen'!A:B,2,0),"") -> #REF! | Q16: =IF(#REF!="Ja",VLOOKUP(A16,'[1]ZArtefakte aus Listen'!A:D,4,0),"") -> #REF!
A17: ZAA_MASS_UP | B17: =VLOOKUP(A17,'Z-Programme'!$A$2:$A$650,1,FALSE) -> ZAA_MASS_UP | C17: Massenänderung Anlagenstamm: Upload CSV-Datei | D17: 1 Ausführbares Programm | E17: Grundsätzlich Nein: für keine Welle relevant | F17: Irrelevant | G17: Finance Gapliste: Gap 01-(A2R-03.06) | H17: Nein, keine Übernahme: Abstimmung mit NTT und Fr. Brahms am 12.3.2024 | I17: Ursprünglich freigegeben im KDB, wird aber nicht mehr benötigt. | K17: Nein, keine Übernahme | L17: Roland, 9.7.2024: Nachträgliche Änderung zum KDB-Beschluss, da Z-Artefakte als obsolet angesehen werden. | N17: =IF(#REF!="Ja",VLOOKUP(A17,'[1]ZArtefakte aus Listen'!A:B,2,0),"") -> #REF! | Q17: =IF(#REF!="Ja",VLOOKUP(A17,'[1]ZArtefakte aus Listen'!A:D,4,0),"") -> #REF!
A18: ZAA_RAHIST01 | B18: =VLOOKUP(A18,'Z-Programme'!$A$2:$A$650,1,FALSE) -> ZAA_RAHIST01 | C18: Anlagenhistorie | D18: 1 Ausführbares Programm | E18: Grundsätzlich Nein: für keine Welle relevant | F18: Irrelevant | J18: X | K18: Nein, keine Übernahme | L18: Roland, 15.11.2023: Nein, Rückführung auf den SAP Standard gemäß Projektvorgabe. | N18: =IF(#REF!="Ja",VLOOKUP(A18,'[1]ZArtefakte aus Listen'!A:B,2,0),"") -> #REF! | Q18: =IF(#REF!="Ja",VLOOKUP(A18,'[1]ZArtefakte aus Listen'!A:D,4,0),"") -> #REF!
A19: ZAA_RAPOST2010 | B19: =VLOOKUP(A19,'Z-Programme'!$A$2:$A$650,1,FALSE) -> ZAA_RAPOST2010 | C19: Buchen der Abschreibungen | D19: 1 Ausführbares Programm | E19: Grundsätzlich Nein: für keine Welle relevant | F19: Irrelevant | J19: X | K19: Nein, keine Übernahme | L19: Roland, 15.11.2023: Nein, Rückführung auf den SAP Standard gemäß Projektvorgabe. | N19: =IF(#REF!="Ja",VLOOKUP(A19,'[1]ZArtefakte aus Listen'!A:B,2,0),"") -> #REF! | Q19: =IF(#REF!="Ja",VLOOKUP(A19,'[1]ZArtefakte aus Listen'!A:D,4,0),"") -> #REF!
A20: ZAA_STAMMDAT_ALV | B20: =VLOOKUP(A20,'Z-Programme'!$A$2:$A$650,1,FALSE) -> ZAA_STAMMDAT_ALV | C20: Stammdaten-Auswertung ALV-Liste ( mehrzeilig ) | D20: 1 Ausführbares Programm | E20: Grundsätzlich Nein: für keine Welle relevant | F20: Irrelevant | G20: Finance Gapliste: Gap 01-(A2R-03.06) | H20: Nein, keine Übernahme: Abstimmung mit NTT und Fr. Brahms am 12.3.2024 | I20: Ursprünglich freigegeben im KDB, wird aber nicht mehr benötigt. | K20: Nein, keine Übernahme | L20: Roland, 9.7.2024: Nachträgliche Änderung zum KDB-Beschluss, da Z-Artefakte als obsolet angesehen werden. | N20: =IF(#REF!="Ja",VLOOKUP(A20,'[1]ZArtefakte aus Listen'!A:B,2,0),"") -> #REF! | Q20: =IF(#REF!="Ja",VLOOKUP(A20,'[1]ZArtefakte aus Listen'!A:D,4,0),"") -> #REF!
A21: ZACAC_DATA_TRANSFER | B21: =VLOOKUP(A21,'Z-Programme'!$A$2:$A$650,1,FALSE) -> ZACAC_DATA_TRANSFER | C21: Übernahme von Debitoren-/Kreditorenrechnungen in die Accrual Engine | D21: 1 Ausführbares Programm | E21: Ja, in Welle 1 relevant | F21: R2R - Abschreibungen Accrual Engine | J21: X | K21: Ja, Übernahme | L21: Roland, 27.5.2024: Ja, wird benötigt, geklärt mit Johannes Schaut | M21: X | N21: =IF(#REF!="Ja",VLOOKUP(A21,'[1]ZArtefakte aus Listen'!A:B,2,0),"") -> #REF! | Q21: =IF(#REF!="Ja",VLOOKUP(A21,'[1]ZArtefakte aus Listen'!A:D,4,0),"") -> #REF!
A22: ZACAC_DSITEMS | B22: =VLOOKUP(A22,'Z-Programme'!$A$2:$A$650,1,FALSE) -> ZACAC_DSITEMS | C22: Anzeigen von Abgrenzungsobjekten + kd.eigene Parameter | D22: 1 Ausführbares Programm | E22: Ja, in Welle 1 relevant | F22: R2R - Abschreibungen Accrual Engine | J22: X | K22: Ja, Übernahme | L22: Roland, 27.5.2024: Ja, wird benötigt, geklärt mit Johannes Schaut | M22: X | N22: =IF(#REF!="Ja",VLOOKUP(A22,'[1]ZArtefakte aus Listen'!A:B,2,0),"") -> #REF! | Q22: =IF(#REF!="Ja",VLOOKUP(A22,'[1]ZArtefakte aus Listen'!A:D,4,0),"") -> #REF!
A23: ZBC_ADDR_CHECK | B23: =VLOOKUP(A23,'Z-Programme'!$A$2:$A$650,1,FALSE) -> ZBC_ADDR_CHECK | C23: Prüfen Debitoren auf fehlende Adresse-Einträge | D23: 1 Ausführbares Programm | E23: Ja, in Welle 1 relevant | F23: Kein Prozess: wird in der ADAC SAP-Basis benötigt. | J23: X | K23: Ja, Übernahme | L23: Roland, 27.5.2024: Funktionalitäten, die auch unter S/4HANA durch die ADAC SAP Basis benötigt werden. | N23: =IF(#REF!="Ja",VLOOKUP(A23,'[1]ZArtefakte aus Listen'!A:B,2,0),"") -> #REF! | Q23: =IF(#REF!="Ja",VLOOKUP(A23,'[1]ZArtefakte aus Listen'!A:D,4,0),"") -> #REF!
A24: ZBC_AL_REORG_OUT | B24: =VLOOKUP(A24,'Z-Programme'!$A$2:$A$650,1,FALSE) -> ZBC_AL_REORG_OUT | C24: Archivelink Reorganisation - Erstellen Löschdatei | D24: 1 Ausführbares Programm | E24: Ja, in Welle 1 relevant | F24: Kein Prozess: wird in der ADAC SAP-Basis benötigt. | J24: X | K24: Ja, Übernahme | L24: Roland, 27.5.2024: Funktionalitäten, die auch unter S/4HANA durch die ADAC SAP Basis benötigt werden. | N24: =IF(#REF!="Ja",VLOOKUP(A24,'[1]ZArtefakte aus Listen'!A:B,2,0),"") -> #REF! | Q24: =IF(#REF!="Ja",VLOOKUP(A24,'[1]ZArtefakte aus Listen'!A:D,4,0),"") -> #REF!
A25: ZBC_AL_REORG_RETURN | B25: =VLOOKUP(A25,'Z-Programme'!$A$2:$A$650,1,FALSE) -> ZBC_AL_REORG_RETURN | C25: Archivelink Reorganisation - Rückantwort NE-Databridge | D25: 1 Ausführbares Programm | E25: Ja, in Welle 1 relevant | F25: Kein Prozess: wird in der ADAC SAP-Basis benötigt. | J25: X | K25: Ja, Übernahme | L25: Roland, 27.5.2024: Funktionalitäten, die auch unter S/4HANA durch die ADAC SAP Basis benötigt werden. | N25: =IF(#REF!="Ja",VLOOKUP(A25,'[1]ZArtefakte aus Listen'!A:B,2,0),"") -> #REF! | Q25: =IF(#REF!="Ja",VLOOKUP(A25,'[1]ZArtefakte aus Listen'!A:D,4,0),"") -> #REF!
A26: ZBC_AL_REORG_VTABS | B26: =VLOOKUP(A26,'Z-Programme'!$A$2:$A$650,1,FALSE) -> ZBC_AL_REORG_VTABS | C26: Archivelink: Pflege der Verknüpfungstabellen | D26: 1 Ausführbares Programm | E26: Ja, in Welle 1 relevant | F26: Kein Prozess: wird in der ADAC SAP-Basis benötigt. | J26: X | K26: Ja, Übernahme | L26: Roland, 27.5.2024: Funktionalitäten, die auch unter S/4HANA durch die ADAC SAP Basis benötigt werden. | N26: =IF(#REF!="Ja",VLOOKUP(A26,'[1]ZArtefakte aus Listen'!A:B,2,0),"") -> #REF! | Q26: =IF(#REF!="Ja",VLOOKUP(A26,'[1]ZArtefakte aus Listen'!A:D,4,0),"") -> #REF!
A27: ZBC_ANONYM_ZQ1 | B27: =VLOOKUP(A27,'Z-Programme'!$A$2:$A$650,1,FALSE) -> ZBC_ANONYM_ZQ1 | C27: Programm ZBC_ANONYM_ZQ1 | D27: 1 Ausführbares Programm | E27: Ja, in Welle 1 relevant | F27: Kein Prozess: wird in der ADAC SAP-Basis benötigt. | J27: X | K27: Ja, Übernahme | L27: Roland, 27.5.2024: Funktionalitäten, die auch unter S/4HANA durch die ADAC SAP Basis benötigt werden. | N27: =IF(#REF!="Ja",VLOOKUP(A27,'[1]ZArtefakte aus Listen'!A:B,2,0),"") -> #REF! | Q27: =IF(#REF!="Ja",VLOOKUP(A27,'[1]ZArtefakte aus Listen'!A:D,4,0),"") -> #REF!
A28: ZBC_BDCLOG_ALV | B28: =VLOOKUP(A28,'Z-Programme'!$A$2:$A$650,1,FALSE) -> ZBC_BDCLOG_ALV | C28: Archivierte BDC Mappenprotokolle anzeigen | D28: 1 Ausführbares Programm | E28: Ja, in Welle 1 relevant | F28: Kein Prozess: wird in der ADAC SAP-Basis benötigt. | J28: X | K28: Ja, Übernahme | L28: Roland, 27.5.2024: Funktionalitäten, die auch unter S/4HANA durch die ADAC SAP Basis benötigt werden. | N28: =IF(#REF!="Ja",VLOOKUP(A28,'[1]ZArtefakte aus Listen'!A:B,2,0),"") -> #REF! | Q28: =IF(#REF!="Ja",VLOOKUP(A28,'[1]ZArtefakte aus Listen'!A:D,4,0),"") -> #REF!
A29: ZBC_BDCLOG_ARCHIVE | B29: =VLOOKUP(A29,'Z-Programme'!$A$2:$A$650,1,FALSE) -> ZBC_BDCLOG_ARCHIVE | C29: BDC Mappenprotokolle archivieren | D29: 1 Ausführbares Programm | E29: Ja, in Welle 1 relevant | F29: Kein Prozess: wird in der ADAC SAP-Basis benötigt. | J29: X | K29: Ja, Übernahme | L29: Roland, 27.5.2024: Funktionalitäten, die auch unter S/4HANA durch die ADAC SAP Basis benötigt werden. | N29: =IF(#REF!="Ja",VLOOKUP(A29,'[1]ZArtefakte aus Listen'!A:B,2,0),"") -> #REF! | Q29: =IF(#REF!="Ja",VLOOKUP(A29,'[1]ZArtefakte aus Listen'!A:D,4,0),"") -> #REF!
A30: ZBC_BDCLOG_ARCHIVE_FIX | B30: =VLOOKUP(A30,'Z-Programme'!$A$2:$A$650,1,FALSE) -> ZBC_BDCLOG_ARCHIVE_FIX | C30: BDC Mappenprotokolle archiv Objekte importieren | D30: 1 Ausführbares Programm | E30: Ja, in Welle 1 relevant | F30: Kein Prozess: wird in der ADAC SAP-Basis benötigt. | J30: X | K30: Ja, Übernahme | L30: Roland, 27.5.2024: Funktionalitäten, die auch unter S/4HANA durch die ADAC SAP Basis benötigt werden. | N30: =IF(#REF!="Ja",VLOOKUP(A30,'[1]ZArtefakte aus Listen'!A:B,2,0),"") -> #REF! | Q30: =IF(#REF!="Ja",VLOOKUP(A30,'[1]ZArtefakte aus Listen'!A:D,4,0),"") -> #REF!
A31: ZBC_BELEG_VOLUME | B31: =VLOOKUP(A31,'Z-Programme'!$A$2:$A$650,1,FALSE) -> ZBC_BELEG_VOLUME | C31: Anzahl Positionen von Belegarten für ECC-Systeme | D31: 1 Ausführbares Programm | E31: Ja, in Welle 1 relevant | F31: Kein Prozess: wird in der ADAC SAP-Basis benötigt. | J31: X | K31: Ja, Übernahme | L31: Roland, 27.5.2024: Funktionalitäten, die auch unter S/4HANA durch die ADAC SAP Basis benötigt werden. | N31: =IF(#REF!="Ja",VLOOKUP(A31,'[1]ZArtefakte aus Listen'!A:B,2,0),"") -> #REF! | Q31: =IF(#REF!="Ja",VLOOKUP(A31,'[1]ZArtefakte aus Listen'!A:D,4,0),"") -> #REF!
A32: ZBC_CALL_PROCEDURE | B32: =VLOOKUP(A32,'Z-Programme'!$A$2:$A$650,1,FALSE) -> ZBC_CALL_PROCEDURE | C32: Aufruf einer "Stored Procedure" in der Berichtswesendatenbank | D32: 1 Ausführbares Programm | E32: Grundsätzlich Nein: für keine Welle relevant | F32: Irrelevant | J32: X | K32: Nein, keine Übernahme | L32: Roland: 22.03.2024: Nein, entfällt, da neue Lösung | N32: =IF(#REF!="Ja",VLOOKUP(A32,'[1]ZArtefakte aus Listen'!A:B,2,0),"") -> #REF! | Q32: =IF(#REF!="Ja",VLOOKUP(A32,'[1]ZArtefakte aus Listen'!A:D,4,0),"") -> #REF!
A33: ZBC_CHECK_NRIV | B33: =VLOOKUP(A33,'Z-Programme'!$A$2:$A$650,1,FALSE) -> ZBC_CHECK_NRIV | C33: Nummernkreise prüfen | D33: 1 Ausführbares Programm | E33: Ja, in Welle 1 relevant | F33: Kein Prozess: wird in der ADAC SAP-Basis benötigt. | J33: X | K33: Ja, Übernahme | L33: Roland, 27.5.2024: Funktionalitäten, die auch unter S/4HANA durch die ADAC SAP Basis benötigt werden. | N33: =IF(#REF!="Ja",VLOOKUP(A33,'[1]ZArtefakte aus Listen'!A:B,2,0),"") -> #REF! | Q33: =IF(#REF!="Ja",VLOOKUP(A33,'[1]ZArtefakte aus Listen'!A:D,4,0),"") -> #REF!
A34: ZBC_COPY_DATASET | B34: =VLOOKUP(A34,'Z-Programme'!$A$2:$A$650,1,FALSE) -> ZBC_COPY_DATASET | C34: Kopieren Dataset mit Archivierung | D34: 1 Ausführbares Programm | E34: Ja, in Welle 1 relevant | F34: Kein Prozess: wird in der ADAC SAP-Basis benötigt. | J34: X | K34: Ja, Übernahme | L34: Roland, 27.5.2024: Funktionalitäten, die auch unter S/4HANA durch die ADAC SAP Basis benötigt werden. | N34: =IF(#REF!="Ja",VLOOKUP(A34,'[1]ZArtefakte aus Listen'!A:B,2,0),"") -> #REF! | Q34: =IF(#REF!="Ja",VLOOKUP(A34,'[1]ZArtefakte aus Listen'!A:D,4,0),"") -> #REF!
... A42: ZBC_JOB_ABORT | B42: =VLOOKUP(A42,'Z-Programme'!$A$2:$A$650,1,FALSE) -> ZBC_JOB_ABORT | C42: Job Abbrechen wenn eine Liste best. String enthält | D42: 1 Ausführbares Programm | E42: Ja, in Welle 1 relevant | F42: Kein Prozess: wird in der ADAC SAP-Basis benötigt. | J42: X | K42: Ja, Übernahme | L42: Roland, 27.5.2024: Funktionalitäten, die auch unter S/4HANA durch die ADAC SAP Basis benötigt werden. | N42: =IF(#REF!="Ja",VLOOKUP(A42,'[1]ZArtefakte aus Listen'!A:B,2,0),"") -> #REF! | Q42: =IF(#REF!="Ja",VLOOKUP(A42,'[1]ZArtefakte aus Listen'!A:D,4,0),"") -> #REF!
A43: ZBC_JOBCONTROL | B43: =VLOOKUP(A43,'Z-Programme'!$A$2:$A$650,1,FALSE) -> ZBC_JOBCONTROL | D43: 1 Ausführbares Programm | E43: Ja, in Welle 1 relevant | F43: Kein Prozess: wird in der ADAC SAP-Basis benötigt. | J43: X | K43: Ja, Übernahme | L43: Roland, 27.5.2024: Funktionalitäten, die auch unter S/4HANA durch die ADAC SAP Basis benötigt werden. | N43: =IF(#REF!="Ja",VLOOKUP(A43,'[1]ZArtefakte aus Listen'!A:B,2,0),"") -> #REF! | Q43: =IF(#REF!="Ja",VLOOKUP(A43,'[1]ZArtefakte aus Listen'!A:D,4,0),"") -> #REF!
A44: ZBC_LOEVM_DEBI_KREDI | B44: =VLOOKUP(A44,'Z-Programme'!$A$2:$A$650,1,FALSE) -> ZBC_LOEVM_DEBI_KREDI | C44: Programm zur Pflege der Löschvormerkung für Debitoren und Kreditoren | D44: 1 Ausführbares Programm | E44: Ja, in Welle 1 relevant | F44: Kein Prozess: wird in der ADAC SAP-Basis benötigt. | J44: X | K44: Ja, Übernahme | L44: Roland, 27.5.2024: Funktionalitäten, die auch unter S/4HANA durch die ADAC SAP Basis benötigt werden. | N44: =IF(#REF!="Ja",VLOOKUP(A44,'[1]ZArtefakte aus Listen'!A:B,2,0),"") -> #REF! | Q44: =IF(#REF!="Ja",VLOOKUP(A44,'[1]ZArtefakte aus Listen'!A:D,4,0),"") -> #REF!
A45: ZBC_LOEVM_DEBI_KREDI_2 | B45: =VLOOKUP(A45,'Z-Programme'!$A$2:$A$650,1,FALSE) -> ZBC_LOEVM_DEBI_KREDI_2 | C45: Setzen Löschvormerkung anhand Tage ohne Buchungen | D45: 1 Ausführbares Programm | E45: Ja, in Welle 1 relevant | F45: Kein Prozess: wird in der ADAC SAP-Basis benötigt. | J45: X | K45: Ja, Übernahme | L45: Roland, 27.5.2024: Funktionalitäten, die auch unter S/4HANA durch die ADAC SAP Basis benötigt werden. | N45: =IF(#REF!="Ja",VLOOKUP(A45,'[1]ZArtefakte aus Listen'!A:B,2,0),"") -> #REF! | Q45: =IF(#REF!="Ja",VLOOKUP(A45,'[1]ZArtefakte aus Listen'!A:D,4,0),"") -> #REF!
A46: ZBC_LOGO_SWITCH | B46: =VLOOKUP(A46,'Z-Programme'!$A$2:$A$650,1,FALSE) -> ZBC_LOGO_SWITCH | C46: Logo-Clicks ein/ausschalten | D46: 1 Ausführbares Programm | E46: Ja, in Welle 1 relevant | F46: Kein Prozess: wird in der ADAC SAP-Basis benötigt. | J46: X | K46: Ja, Übernahme | L46: Roland, 27.5.2024: Funktionalitäten, die auch unter S/4HANA durch die ADAC SAP Basis benötigt werden. | N46: =IF(#REF!="Ja",VLOOKUP(A46,'[1]ZArtefakte aus Listen'!A:B,2,0),"") -> #REF! | Q46: =IF(#REF!="Ja",VLOOKUP(A46,'[1]ZArtefakte aus Listen'!A:D,4,0),"") -> #REF!
A47: ZBC_MAESTRO | B47: =VLOOKUP(A47,'Z-Programme'!$A$2:$A$650,1,FALSE) -> ZBC_MAESTRO | C47: ZBC_MAESTRO | D47: 1 Ausführbares Programm | E47: Grundsätzlich Nein: für keine Welle relevant | F47: Irrelevant | J47: X | K47: Nein, keine Übernahme | L47: Roland: 22.03.2024: Nein, entfällt, da neue Lösung | N47: =IF(#REF!="Ja",VLOOKUP(A47,'[1]ZArtefakte aus Listen'!A:B,2,0),"") -> #REF! | Q47: =IF(#REF!="Ja",VLOOKUP(A47,'[1]ZArtefakte aus Listen'!A:D,4,0),"") -> #REF!
A48: ZBC_NACH_UPDATE_TESTSYSTEM | B48: =VLOOKUP(A48,'Z-Programme'!$A$2:$A$650,1,FALSE) -> ZBC_NACH_UPDATE_TESTSYSTEM | C48: Update Tabelle NACH im Test-System ("Sofort ausgeben", "Ausgabegerät") | D48: 1 Ausführbares Programm | E48: Ja, in Welle 1 relevant | F48: Kein Prozess: wird in der ADAC SAP-Basis benötigt. | J48: X | K48: Ja, Übernahme | L48: Roland, 27.5.2024: Funktionalitäten, die auch unter S/4HANA durch die ADAC SAP Basis benötigt werden. | N48: =IF(#REF!="Ja",VLOOKUP(A48,'[1]ZArtefakte aus Listen'!A:B,2,0),"") -> #REF! | Q48: =IF(#REF!="Ja",VLOOKUP(A48,'[1]ZArtefakte aus Listen'!A:D,4,0),"") -> #REF!
A49: ZBC_NOTFALLUSERAKTIEVIERUNG | B49: =VLOOKUP(A49,'Z-Programme'!$A$2:$A$650,1,FALSE) -> ZBC_NOTFALLUSERAKTIEVIERUNG | C49: Programm zur automatischen Userinaktivierung | D49: 1 Ausführbares Programm | E49: Ja, in Welle 1 relevant | F49: Kein Prozess: wird in der ADAC SAP-Basis benötigt. | J49: X | K49: Ja, Übernahme | L49: Roland, 27.5.2024: Funktionalitäten, die auch unter S/4HANA durch die ADAC SAP Basis benötigt werden. | N49: =IF(#REF!="Ja",VLOOKUP(A49,'[1]ZArtefakte aus Listen'!A:B,2,0),"") -> #REF! | Q49: =IF(#REF!="Ja",VLOOKUP(A49,'[1]ZArtefakte aus Listen'!A:D,4,0),"") -> #REF!
A50: ZBC_OREA_COA | B50: =VLOOKUP(A50,'Z-Programme'!$A$2:$A$650,1,FALSE) -> ZBC_OREA_COA | C50: Füllen der COA-Tabellen | D50: 1 Ausführbares Programm | E50: Ja, in Welle 1 relevant | F50: I2C | G50: Finance Gapliste: Gap O2C | K50: Ja, Übernahme, da Z-Artefakt aus Ramp-Up-Phase: freigegeben durch KDB | N50: =IF(#REF!="Ja",VLOOKUP(A50,'[1]ZArtefakte aus Listen'!A:B,2,0),"") -> #REF! | Q50: =IF(#REF!="Ja",VLOOKUP(A50,'[1]ZArtefakte aus Listen'!A:D,4,0),"") -> #REF!
A51: ZBC_OREA_COA_NACHVERARBEITUNG | B51: =VLOOKUP(A51,'Z-Programme'!$A$2:$A$650,1,FALSE) -> ZBC_OREA_COA_NACHVERARBEITUNG | C51: Nachverarbeitung der Freigabehierarchie | D51: 1 Ausführbares Programm | E51: Ja, in Welle 1 relevant | F51: Kein Prozess: wird in der ADAC SAP-Basis benötigt. | J51: X | K51: Ja, Übernahme | L51: Roland, 27.5.2024: Funktionalitäten, die auch unter S/4HANA durch die ADAC SAP Basis benötigt werden. | N51: =IF(#REF!="Ja",VLOOKUP(A51,'[1]ZArtefakte aus Listen'!A:B,2,0),"") -> #REF! | Q51: =IF(#REF!="Ja",VLOOKUP(A51,'[1]ZArtefakte aus Listen'!A:D,4,0),"") -> #REF!
A52: ZBC_OREA_COA_TEST | B52: =VLOOKUP(A52,'Z-Programme'!$A$2:$A$650,1,FALSE) -> ZBC_OREA_COA_TEST | C52: Testutils | D52: 1 Ausführbares Programm | E52: Ja, in Welle 1 relevant | F52: Kein Prozess: wird in der ADAC SAP-Basis benötigt. | J52: X | K52: Ja, Übernahme | L52: Roland, 27.5.2024: Funktionalitäten, die auch unter S/4HANA durch die ADAC SAP Basis benötigt werden. | N52: =IF(#REF!="Ja",VLOOKUP(A52,'[1]ZArtefakte aus Listen'!A:B,2,0),"") -> #REF! | Q52: =IF(#REF!="Ja",VLOOKUP(A52,'[1]ZArtefakte aus Listen'!A:D,4,0),"") -> #REF!
A53: ZBC_OREA_COA_USER_LOESCHEN | B53: =VLOOKUP(A53,'Z-Programme'!$A$2:$A$650,1,FALSE) -> ZBC_OREA_COA_USER_LOESCHEN | C53: Löschen von einzelnen Usern aus der COA | D53: 1 Ausführbares Programm | E53: Ja, in Welle 1 relevant | F53: Kein Prozess: wird in der ADAC SAP-Basis benötigt. | J53: X | K53: Ja, Übernahme | L53: Roland, 27.5.2024: Funktionalitäten, die auch unter S/4HANA durch die ADAC SAP Basis benötigt werden. | N53: =IF(#REF!="Ja",VLOOKUP(A53,'[1]ZArtefakte aus Listen'!A:B,2,0),"") -> #REF! | Q53: =IF(#REF!="Ja",VLOOKUP(A53,'[1]ZArtefakte aus Listen'!A:D,4,0),"") -> #REF!
A54: ZBC_OREA_FREIGEBER_TEST | B54: =VLOOKUP(A54,'Z-Programme'!$A$2:$A$650,1,FALSE) -> ZBC_OREA_FREIGEBER_TEST | C54: Test des Freigeberfunktionsbausteins | D54: 1 Ausführbares Programm | E54: Ja, in Welle 1 relevant | F54: I2C | G54: Finance Gapliste: Gap O2C | K54: Ja, Übernahme, da Z-Artefakt aus Ramp-Up-Phase: freigegeben durch KDB | N54: =IF(#REF!="Ja",VLOOKUP(A54,'[1]ZArtefakte aus Listen'!A:B,2,0),"") -> #REF! | Q54: =IF(#REF!="Ja",VLOOKUP(A54,'[1]ZArtefakte aus Listen'!A:D,4,0),"") -> #REF!
A55: ZBC_SET_TVARVC | B55: =VLOOKUP(A55,'Z-Programme'!$A$2:$A$650,1,FALSE) -> ZBC_SET_TVARVC | C55: Parameter in TVARVC belegen und updaten | D55: 1 Ausführbares Programm | E55: Ja, in Welle 1 relevant | F55: Kein Prozess: wird in der ADAC SAP-Basis benötigt. | J55: X | K55: Ja, Übernahme | L55: Roland, 27.5.2024: Funktionalitäten, die auch unter S/4HANA durch die ADAC SAP Basis benötigt werden. | N55: =IF(#REF!="Ja",VLOOKUP(A55,'[1]ZArtefakte aus Listen'!A:B,2,0),"") -> #REF! | Q55: =IF(#REF!="Ja",VLOOKUP(A55,'[1]ZArtefakte aus Listen'!A:D,4,0),"") -> #REF!
A56: ZBC_SPERR_STAMM_DS | B56: =VLOOKUP(A56,'Z-Programme'!$A$2:$A$650,1,FALSE) -> ZBC_SPERR_STAMM_DS | C56: Datenschutz: Pflege Berechtigungsgruppe im Stammsatz | D56: 1 Ausführbares Programm | E56: Ja, in Welle 1 relevant | F56: Kein Prozess: wird in der ADAC SAP-Basis benötigt. | J56: X | K56: Ja, Übernahme | L56: Roland, 27.5.2024: Funktionalitäten, die auch unter S/4HANA durch die ADAC SAP Basis benötigt werden. | N56: =IF(#REF!="Ja",VLOOKUP(A56,'[1]ZArtefakte aus Listen'!A:B,2,0),"") -> #REF! | Q56: =IF(#REF!="Ja",VLOOKUP(A56,'[1]ZArtefakte aus Listen'!A:D,4,0),"") -> #REF!
A57: ZBC_SPOOL_ARCHIV | B57: =VLOOKUP(A57,'Z-Programme'!$A$2:$A$650,1,FALSE) -> ZBC_SPOOL_ARCHIV | C57: Drucklistenarchivierung | D57: 1 Ausführbares Programm | E57: Ja, in Welle 1 relevant | F57: Kein Prozess: wird in der ADAC SAP-Basis benötigt. | J57: X | K57: Ja, Übernahme | L57: Roland, 27.5.2024: Funktionalitäten, die auch unter S/4HANA durch die ADAC SAP Basis benötigt werden. | N57: =IF(#REF!="Ja",VLOOKUP(A57,'[1]ZArtefakte aus Listen'!A:B,2,0),"") -> #REF! | Q57: =IF(#REF!="Ja",VLOOKUP(A57,'[1]ZArtefakte aus Listen'!A:D,4,0),"") -> #REF!
A58: ZBC_SPOOL_OUTPUT | B58: =VLOOKUP(A58,'Z-Programme'!$A$2:$A$650,1,FALSE) -> ZBC_SPOOL_OUTPUT | C58: Zusätzliches Ausgeben / Senden von Spoollisten | D58: 1 Ausführbares Programm | E58: Ja, in Welle 1 relevant | F58: Kein Prozess: wird in der ADAC SAP-Basis benötigt. | J58: X | K58: Ja, Übernahme | L58: Roland, 27.5.2024: Funktionalitäten, die auch unter S/4HANA durch die ADAC SAP Basis benötigt werden. | N58: =IF(#REF!="Ja",VLOOKUP(A58,'[1]ZArtefakte aus Listen'!A:B,2,0),"") -> #REF! | Q58: =IF(#REF!="Ja",VLOOKUP(A58,'[1]ZArtefakte aus Listen'!A:D,4,0),"") -> #REF!
A59: ZBC_SPOOL_PCOUNT | B59: =VLOOKUP(A59,'Z-Programme'!$A$2:$A$650,1,FALSE) -> ZBC_SPOOL_PCOUNT | C59: Ermittlung Seitenanzahl und Ausgabe von Spool-Datasets | D59: 1 Ausführbares Programm | E59: Ja, in Welle 1 relevant | F59: Kein Prozess: wird in der ADAC SAP-Basis benötigt. | J59: X | K59: Ja, Übernahme | L59: Roland, 27.5.2024: Funktionalitäten, die auch unter S/4HANA durch die ADAC SAP Basis benötigt werden. | N59: =IF(#REF!="Ja",VLOOKUP(A59,'[1]ZArtefakte aus Listen'!A:B,2,0),"") -> #REF! | Q59: =IF(#REF!="Ja",VLOOKUP(A59,'[1]ZArtefakte aus Listen'!A:D,4,0),"") -> #REF!
A60: ZBC_ST03N | B60: =VLOOKUP(A60,'Z-Programme'!$A$2:$A$650,1,FALSE) -> ZBC_ST03N | C60: Auswertung Systemlast | D60: 1 Ausführbares Programm | E60: Ja, in Welle 1 relevant | F60: Kein Prozess: wird in der ADAC SAP-Basis benötigt. | J60: X | K60: Ja, Übernahme | L60: Roland, 27.5.2024: Funktionalitäten, die auch unter S/4HANA durch die ADAC SAP Basis benötigt werden. | N60: =IF(#REF!="Ja",VLOOKUP(A60,'[1]ZArtefakte aus Listen'!A:B,2,0),"") -> #REF! | Q60: =IF(#REF!="Ja",VLOOKUP(A60,'[1]ZArtefakte aus Listen'!A:D,4,0),"") -> #REF!
A61: ZBC_TAB_EXPIMP | B61: =VLOOKUP(A61,'Z-Programme'!$A$2:$A$650,1,FALSE) -> ZBC_TAB_EXPIMP | C61: ZBC_TAB_EXPIMP Tabellen Exportieren/Importieren | D61: 1 Ausführbares Programm | E61: Ja, in Welle 1 relevant | F61: Kein Prozess: wird in der ADAC SAP-Basis benötigt. | J61: X | K61: Ja, Übernahme | L61: Roland, 27.5.2024: Funktionalitäten, die auch unter S/4HANA durch die ADAC SAP Basis benötigt werden. | N61: =IF(#REF!="Ja",VLOOKUP(A61,'[1]ZArtefakte aus Listen'!A:B,2,0),"") -> #REF! | Q61: =IF(#REF!="Ja",VLOOKUP(A61,'[1]ZArtefakte aus Listen'!A:D,4,0),"") -> #REF!
A62: ZBC_TABELLEN_TRANSFER | B62: =VLOOKUP(A62,'Z-Programme'!$A$2:$A$650,1,FALSE) -> ZBC_TABELLEN_TRANSFER | C62: Programm ZBC_TABELLEN_TRANSFER | D62: 1 Ausführbares Programm | E62: Ja, in Welle 1 relevant | F62: Kein Prozess: wird in der ADAC SAP-Basis benötigt. | J62: X | K62: Ja, Übernahme | L62: Roland, 27.5.2024: Funktionalitäten, die auch unter S/4HANA durch die ADAC SAP Basis benötigt werden. | N62: =IF(#REF!="Ja",VLOOKUP(A62,'[1]ZArtefakte aus Listen'!A:B,2,0),"") -> #REF! | Q62: =IF(#REF!="Ja",VLOOKUP(A62,'[1]ZArtefakte aus Listen'!A:D,4,0),"") -> #REF!
A63: ZBC_USERINAKTIVIERUNG | B63: =VLOOKUP(A63,'Z-Programme'!$A$2:$A$650,1,FALSE) -> ZBC_USERINAKTIVIERUNG | C63: Programm zur automatischen Userinaktivierung | D63: 1 Ausführbares Programm | E63: Ja, in Welle 1 relevant | F63: Basis | G63: Finance Gapliste: Gap O2C | K63: Ja, Übernahme, da Z-Artefakt aus Ramp-Up-Phase: freigegeben durch KDB | L63: Roland, 8.7.2024: Ist eine Anforderung der Revision, muss umgesetzt werden. Klärung mit Johannes Schaut. | N63: =IF(#REF!="Ja",VLOOKUP(A63,'[1]ZArtefakte aus Listen'!A:B,2,0),"") -> #REF! | Q63: =IF(#REF!="Ja",VLOOKUP(A63,'[1]ZArtefakte aus Listen'!A:D,4,0),"") -> #REF!
A64: ZBC_VARIANT_LIST | B64: =VLOOKUP(A64,'Z-Programme'!$A$2:$A$650,1,FALSE) -> ZBC_VARIANT_LIST | C64: Reportvarianten-Scanfunktionalität | D64: 1 Ausführbares Programm | E64: Ja, in Welle 1 relevant | F64: Kein Prozess: wird in der ADAC SAP-Basis benötigt. | J64: X | K64: Ja, Übernahme | L64: Roland, 27.5.2024: Funktionalitäten, die auch unter S/4HANA durch die ADAC SAP Basis benötigt werden. | N64: =IF(#REF!="Ja",VLOOKUP(A64,'[1]ZArtefakte aus Listen'!A:B,2,0),"") -> #REF! | Q64: =IF(#REF!="Ja",VLOOKUP(A64,'[1]ZArtefakte aus Listen'!A:D,4,0),"") -> #REF!
A65: ZBC_VARIANT_LIST_ALV | B65: =VLOOKUP(A65,'Z-Programme'!$A$2:$A$650,1,FALSE) -> ZBC_VARIANT_LIST_ALV | C65: Reportvarianten-Scanfunktionalität | D65: 1 Ausführbares Programm | E65: Ja, in Welle 1 relevant | F65: Kein Prozess: wird in der ADAC SAP-Basis benötigt. | J65: X | K65: Ja, Übernahme | L65: Roland, 27.5.2024: Funktionalitäten, die auch unter S/4HANA durch die ADAC SAP Basis benötigt werden. | N65: =IF(#REF!="Ja",VLOOKUP(A65,'[1]ZArtefakte aus Listen'!A:B,2,0),"") -> #REF! | Q65: =IF(#REF!="Ja",VLOOKUP(A65,'[1]ZArtefakte aus Listen'!A:D,4,0),"") -> #REF!
A66: ZBC_ZEMAREP_FRGREORG | B66: =VLOOKUP(A66,'Z-Programme'!$A$2:$A$650,1,FALSE) -> ZBC_ZEMAREP_FRGREORG | C66: Reorg Tabelle ZBC_ZEMAREP_FRG | D66: 1 Ausführbares Programm | E66: Ja, in Welle 1 relevant | F66: Basis | G66: Finance Gapliste: Gap O2C | K66: Ja, Übernahme, da Z-Artefakt aus Ramp-Up-Phase: freigegeben durch KDB | L66: Roland, 8.7.2024: Ist Prozessthema für die Anlage der User. Klärung mit Johannes Schaut. | N66: =IF(#REF!="Ja",VLOOKUP(A66,'[1]ZArtefakte aus Listen'!A:B,2,0),"") -> #REF! | Q66: =IF(#REF!="Ja",VLOOKUP(A66,'[1]ZArtefakte aus Listen'!A:D,4,0),"") -> #REF!
A67: ZBC_ZEMAREP_GET | B67: =VLOOKUP(A67,'Z-Programme'!$A$2:$A$650,1,FALSE) -> ZBC_ZEMAREP_GET | C67: lesen zemarep | D67: 1 Ausführbares Programm | E67: Ja, in Welle 1 relevant | F67: Basis | G67: Finance Gapliste: Gap O2C | K67: Ja, Übernahme, da Z-Artefakt aus Ramp-Up-Phase: freigegeben durch KDB | L67: Roland, 8.7.2024: Ist Prozessthema für die Anlage der User. Klärung mit Johannes Schaut. | N67: =IF(#REF!="Ja",VLOOKUP(A67,'[1]ZArtefakte aus Listen'!A:B,2,0),"") -> #REF! | Q67: =IF(#REF!="Ja",VLOOKUP(A67,'[1]ZArtefakte aus Listen'!A:D,4,0),"") -> #REF!
A68: ZBC_ZEMAREP_USER | B68: =VLOOKUP(A68,'Z-Programme'!$A$2:$A$650,1,FALSE) -> ZBC_ZEMAREP_USER | C68: ZEMAREP User-Pflege | D68: 1 Ausführbares Programm | E68: Ja, in Welle 1 relevant | F68: Basis | G68: Finance Gapliste: Gap O2C | K68: Ja, Übernahme, da Z-Artefakt aus Ramp-Up-Phase: freigegeben durch KDB | L68: Roland, 8.7.2024: Ist Prozessthema für die Anlage der User. Klärung mit Johannes Schaut. | N68: =IF(#REF!="Ja",VLOOKUP(A68,'[1]ZArtefakte aus Listen'!A:B,2,0),"") -> #REF! | Q68: =IF(#REF!="Ja",VLOOKUP(A68,'[1]ZArtefakte aus Listen'!A:D,4,0),"") -> #REF!
A69: ZBC_ZEMAREP_USERCHG_REO | B69: =VLOOKUP(A69,'Z-Programme'!$A$2:$A$650,1,FALSE) -> ZBC_ZEMAREP_USERCHG_REO | C69: Anzeige/Löschen Tabelle ZREP_USERCHG | D69: 1 Ausführbares Programm | E69: Ja, in Welle 1 relevant | F69: Basis | G69: Finance Gapliste: Gap O2C | K69: Ja, Übernahme, da Z-Artefakt aus Ramp-Up-Phase: freigegeben durch KDB | L69: Roland, 8.7.2024: Ist Prozessthema für die Anlage der User. Klärung mit Johannes Schaut. | N69: =IF(#REF!="Ja",VLOOKUP(A69,'[1]ZArtefakte aus Listen'!A:B,2,0),"") -> #REF! | Q69: =IF(#REF!="Ja",VLOOKUP(A69,'[1]ZArtefakte aus Listen'!A:D,4,0),"") -> #REF!
A70: ZBC_ZEMAREP_USRGUELT | B70: =VLOOKUP(A70,'Z-Programme'!$A$2:$A$650,1,FALSE) -> ZBC_ZEMAREP_USRGUELT | C70: user gültigkeit prüfen | D70: 1 Ausführbares Programm | E70: Ja, in Welle 1 relevant | F70: Basis | G70: Finance Gapliste: Gap O2C | K70: Ja, Übernahme, da Z-Artefakt aus Ramp-Up-Phase: freigegeben durch KDB | L70: Roland, 8.7.2024: Ist Prozessthema für die Anlage der User. Klärung mit Johannes Schaut. | N70: =IF(#REF!="Ja",VLOOKUP(A70,'[1]ZArtefakte aus Listen'!A:B,2,0),"") -> #REF! | Q70: =IF(#REF!="Ja",VLOOKUP(A70,'[1]ZArtefakte aus Listen'!A:D,4,0),"") -> #REF!
A71: ZBC_ZRSLG_SERVERS_1692951 | B71: =VLOOKUP(A71,'Z-Programme'!$A$2:$A$650,1,FALSE) -> ZBC_ZRSLG_SERVERS_1692951 | C71: Korrekturprogramm Upgrade SNOTE 2164430 | D71: 1 Ausführbares Programm | E71: Ja, in Welle 1 relevant | F71: Kein Prozess: wird in der ADAC SAP-Basis benötigt. | J71: X | K71: Ja, Übernahme | L71: Roland, 27.5.2024: Funktionalitäten, die auch unter S/4HANA durch die ADAC SAP Basis benötigt werden. | N71: =IF(#REF!="Ja",VLOOKUP(A71,'[1]ZArtefakte aus Listen'!A:B,2,0),"") -> #REF! | Q71: =IF(#REF!="Ja",VLOOKUP(A71,'[1]ZArtefakte aus Listen'!A:D,4,0),"") -> #REF!
A72: ZBC_ZRUTDDLSLDEL_2163340 | B72: =VLOOKUP(A72,'Z-Programme'!$A$2:$A$650,1,FALSE) -> ZBC_ZRUTDDLSLDEL_2163340 | C72: Korrekturprogramm Upgrade SNOTE 2164430 | D72: 1 Ausführbares Programm | E72: Ja, in Welle 1 relevant | F72: Kein Prozess: wird in der ADAC SAP-Basis benötigt. | J72: X | K72: Ja, Übernahme | L72: Roland, 27.5.2024: Funktionalitäten, die auch unter S/4HANA durch die ADAC SAP Basis benötigt werden. | N72: =IF(#REF!="Ja",VLOOKUP(A72,'[1]ZArtefakte aus Listen'!A:B,2,0),"") -> #REF! | Q72: =IF(#REF!="Ja",VLOOKUP(A72,'[1]ZArtefakte aus Listen'!A:D,4,0),"") -> #REF!
A73: ZCA_MAIL2 | B73: =VLOOKUP(A73,'Z-Programme'!$A$2:$A$650,1,FALSE) -> ZCA_MAIL2 | C73: Globale Routinen Luftrettung | D73: 1 Ausführbares Programm | E73: Ja, in Welle 1 relevant | F73: Kein Prozess: wird in der ADAC SAP-Basis benötigt. | J73: X | K73: Ja, Übernahme | L73: Roland, 27.5.2024: Funktionalitäten, die auch unter S/4HANA durch die ADAC SAP Basis benötigt werden. | N73: =IF(#REF!="Ja",VLOOKUP(A73,'[1]ZArtefakte aus Listen'!A:B,2,0),"") -> #REF! | Q73: =IF(#REF!="Ja",VLOOKUP(A73,'[1]ZArtefakte aus Listen'!A:D,4,0),"") -> #REF!
A74: ZCA_MAPPCHECK | B74: =VLOOKUP(A74,'Z-Programme'!$A$2:$A$650,1,FALSE) -> ZCA_MAPPCHECK | C74: Mappenstatus | D74: 1 Ausführbares Programm | E74: Ja, in Welle 1 relevant | F74: Kein Prozess: wird in der ADAC SAP-Basis benötigt. | J74: X | K74: Ja, Übernahme | L74: Roland, 27.5.2024: Funktionalitäten, die auch unter S/4HANA durch die ADAC SAP Basis benötigt werden. | N74: =IF(#REF!="Ja",VLOOKUP(A74,'[1]ZArtefakte aus Listen'!A:B,2,0),"") -> #REF! | Q74: =IF(#REF!="Ja",VLOOKUP(A74,'[1]ZArtefakte aus Listen'!A:D,4,0),"") -> #REF!
A75: ZCA_TEST_GOS | B75: =VLOOKUP(A75,'Z-Programme'!$A$2:$A$650,1,FALSE) -> ZCA_TEST_GOS | C75: Testprogramm | D75: 1 Ausführbares Programm | E75: Ja, in Welle 1 relevant | F75: Kein Prozess: wird in der ADAC SAP-Basis benötigt. | J75: X | K75: Ja, Übernahme | L75: Roland, 27.5.2024: Funktionalitäten, die auch unter S/4HANA durch die ADAC SAP Basis benötigt werden. | N75: =IF(#REF!="Ja",VLOOKUP(A75,'[1]ZArtefakte aus Listen'!A:B,2,0),"") -> #REF! | Q75: =IF(#REF!="Ja",VLOOKUP(A75,'[1]ZArtefakte aus Listen'!A:D,4,0),"") -> #REF!
A76: ZCA_WARTEN | B76: =VLOOKUP(A76,'Z-Programme'!$A$2:$A$650,1,FALSE) -> ZCA_WARTEN | C76: Warten n Minuten (max. 30) | D76: 1 Ausführbares Programm | E76: Ja, in Welle 1 relevant | F76: Kein Prozess: wird in der ADAC SAP-Basis benötigt. | J76: X | K76: Ja, Übernahme | L76: Roland, 27.5.2024: Funktionalitäten, die auch unter S/4HANA durch die ADAC SAP Basis benötigt werden. | N76: =IF(#REF!="Ja",VLOOKUP(A76,'[1]ZArtefakte aus Listen'!A:B,2,0),"") -> #REF! | Q76: =IF(#REF!="Ja",VLOOKUP(A76,'[1]ZArtefakte aus Listen'!A:D,4,0),"") -> #REF!
A77: ZCMFIFU1 | B77: =VLOOKUP(A77,'Z-Programme'!$A$2:$A$650,1,FALSE) -> ZCMFIFU1 | C77: OSS: 156239 Report Datenaufbau Banksalden | D77: 1 Ausführbares Programm | E77: Grundsätzlich Nein: für keine Welle relevant | F77: Irrelevant | J77: X | K77: Nein, keine Übernahme | L77: Roland, 15.11.2023: Nein, bezieht sich auf einen OSS Hinweis aus 2015. | N77: =IF(#REF!="Ja",VLOOKUP(A77,'[1]ZArtefakte aus Listen'!A:B,2,0),"") -> #REF! | Q77: =IF(#REF!="Ja",VLOOKUP(A77,'[1]ZArtefakte aus Listen'!A:D,4,0),"") -> #REF!
A78: ZCO_ABSTIMMUNG | B78: =VLOOKUP(A78,'Z-Programme'!$A$2:$A$650,1,FALSE) -> ZCO_ABSTIMMUNG | C78: Abstimmung Intercompany | D78: 1 Ausführbares Programm | E78: Grundsätzlich Nein: für keine Welle relevant | F78: Irrelevant | J78: X | K78: Nein, keine Übernahme | L78: Roland, 23.2.2024: Nein, wird nicht mehr benötigt lt. P2P-Team. | N78: =IF(#REF!="Ja",VLOOKUP(A78,'[1]ZArtefakte aus Listen'!A:B,2,0),"") -> #REF! | Q78: =IF(#REF!="Ja",VLOOKUP(A78,'[1]ZArtefakte aus Listen'!A:D,4,0),"") -> #REF!
A79: ZCO_ABSTIMMUNG_ARCHIVLINK | B79: =VLOOKUP(A79,'Z-Programme'!$A$2:$A$650,1,FALSE) -> ZCO_ABSTIMMUNG_ARCHIVLINK | C79: FI: Archiv_Link_Rechnungsbeleg: FI-Rechnungsdruck | D79: 1 Ausführbares Programm | E79: Grundsätzlich Nein: für keine Welle relevant | F79: Irrelevant | J79: X | K79: Nein, keine Übernahme | L79: Roland, 23.2.2024: Nein, wird nicht mehr benötigt lt. P2P-Team. | N79: =IF(#REF!="Ja",VLOOKUP(A79,'[1]ZArtefakte aus Listen'!A:B,2,0),"") -> #REF! | Q79: =IF(#REF!="Ja",VLOOKUP(A79,'[1]ZArtefakte aus Listen'!A:D,4,0),"") -> #REF!
A80: ZCO_ABSTIMMUNG_PRUEFUNG | B80: =VLOOKUP(A80,'Z-Programme'!$A$2:$A$650,1,FALSE) -> ZCO_ABSTIMMUNG_PRUEFUNG | C80: Prüfung der CO/FI-Abstimmung | D80: 1 Ausführbares Programm | E80: Grundsätzlich Nein: für keine Welle relevant | F80: Irrelevant | J80: X | K80: Nein, keine Übernahme | L80: Roland, 23.2.2024: Nein, wird nicht mehr benötigt lt. P2P-Team. | N80: =IF(#REF!="Ja",VLOOKUP(A80,'[1]ZArtefakte aus Listen'!A:B,2,0),"") -> #REF! | Q80: =IF(#REF!="Ja",VLOOKUP(A80,'[1]ZArtefakte aus Listen'!A:D,4,0),"") -> #REF!
A81: ZCO_ABZUG_KSTPROJEKT_UMSETZUNG | B81: =VLOOKUP(A81,'Z-Programme'!$A$2:$A$650,1,FALSE) -> ZCO_ABZUG_KSTPROJEKT_UMSETZUNG | C81: Programm ZCO_ABZUG_KSTPROJEKT_UMSETZUNG | D81: 1 Ausführbares Programm | E81: Ja, in Welle 1 relevant | F81: P2P | J81: X | K81: Nein, keine Übernahme | L81: 17.02.25: nicht für Planisware benötigt (s.u.) | N81: =IF(#REF!="Ja",VLOOKUP(A81,'[1]ZArtefakte aus Listen'!A:B,2,0),"") -> #REF! | Q81: =IF(#REF!="Ja",VLOOKUP(A81,'[1]ZArtefakte aus Listen'!A:D,4,0),"") -> #REF!
A82: ZCO_AVM_DATENABZUG | B82: =VLOOKUP(A82,'Z-Programme'!$A$2:$A$650,1,FALSE) -> ZCO_AVM_DATENABZUG | C82: Kostenarten- / Profitcenter-Datenabzug | D82: 1 Ausführbares Programm | E82: Ja, in Welle 1 relevant | F82: P2P | J82: X | K82: Nein, keine Übernahme | L82: 17.02.25: wird von AVM nicht mehr benötigt | N82: =IF(#REF!="Ja",VLOOKUP(A82,'[1]ZArtefakte aus Listen'!A:B,2,0),"") -> #REF! | Q82: =IF(#REF!="Ja",VLOOKUP(A82,'[1]ZArtefakte aus Listen'!A:D,4,0),"") -> #REF!
A83: ZCO_BEWEGUNGSDATEN_ERGRE | B83: =VLOOKUP(A83,'Z-Programme'!$A$2:$A$650,1,FALSE) -> ZCO_BEWEGUNGSDATEN_ERGRE | C83: Initialization und At Selection Screen | D83: 1 Ausführbares Programm | E83: Grundsätzlich Nein: für keine Welle relevant | F83: Irrelevant | J83: X | K83: Nein, keine Übernahme | L83: Roland, 23.2.2024: Nein, wird nicht mehr benötigt lt. P2P-Team. (Ersatz durch BW und SAC) | N83: =IF(#REF!="Ja",VLOOKUP(A83,'[1]ZArtefakte aus Listen'!A:B,2,0),"") -> #REF! | Q83: =IF(#REF!="Ja",VLOOKUP(A83,'[1]ZArtefakte aus Listen'!A:D,4,0),"") -> #REF!
A84: ZCO_DATENABZUG_PCA | B84: =VLOOKUP(A84,'Z-Programme'!$A$2:$A$650,1,FALSE) -> ZCO_DATENABZUG_PCA | D84: 1 Ausführbares Programm | E84: Grundsätzlich Nein: für keine Welle relevant | F84: Irrelevant | J84: X | K84: Nein, keine Übernahme | L84: Roland, 23.2.2024: Nein, wird nicht mehr benötigt lt. P2P-Team. | N84: =IF(#REF!="Ja",VLOOKUP(A84,'[1]ZArtefakte aus Listen'!A:B,2,0),"") -> #REF! | Q84: =IF(#REF!="Ja",VLOOKUP(A84,'[1]ZArtefakte aus Listen'!A:D,4,0),"") -> #REF!
A85: ZCO_DRUCKER_SPOOL | B85: =VLOOKUP(A85,'Z-Programme'!$A$2:$A$650,1,FALSE) -> ZCO_DRUCKER_SPOOL | D85: 1 Ausführbares Programm | E85: Ja, in Welle 1 relevant | F85: P2P | J85: X | K85: Nein, keine Übernahme | L85: 17.02.25 wird in S/4 nicht mehr benötigt | N85: =IF(#REF!="Ja",VLOOKUP(A85,'[1]ZArtefakte aus Listen'!A:B,2,0),"") -> #REF! | Q85: =IF(#REF!="Ja",VLOOKUP(A85,'[1]ZArtefakte aus Listen'!A:D,4,0),"") -> #REF!
A86: ZCO_ERGEBNISRECHNUNG | B86: =VLOOKUP(A86,'Z-Programme'!$A$2:$A$650,1,FALSE) -> ZCO_ERGEBNISRECHNUNG | C86: Datenabzug Controlling für die Ergebnisrechnung | D86: 1 Ausführbares Programm | E86: Grundsätzlich Nein: für keine Welle relevant | F86: Irrelevant | J86: X | K86: Nein, keine Übernahme | L86: Roland, 23.2.2024: Nein, wird nicht mehr benötigt lt. P2P-Team. | N86: =IF(#REF!="Ja",VLOOKUP(A86,'[1]ZArtefakte aus Listen'!A:B,2,0),"") -> #REF! | Q86: =IF(#REF!="Ja",VLOOKUP(A86,'[1]ZArtefakte aus Listen'!A:D,4,0),"") -> #REF!
A87: ZCO_HIERARCHIEPRUEFUNG | B87: =VLOOKUP(A87,'Z-Programme'!$A$2:$A$650,1,FALSE) -> ZCO_HIERARCHIEPRUEFUNG | C87: Programm ZCO_HIERARCHIEPRUEFUNG | D87: 1 Ausführbares Programm | E87: Grundsätzlich Nein: für keine Welle relevant | F87: Irrelevant | J87: X | K87: Nein, keine Übernahme | L87: Roland, 23.2.2024: Nein, wird nicht mehr benötigt lt. P2P-Team. | N87: =IF(#REF!="Ja",VLOOKUP(A87,'[1]ZArtefakte aus Listen'!A:B,2,0),"") -> #REF! | Q87: =IF(#REF!="Ja",VLOOKUP(A87,'[1]ZArtefakte aus Listen'!A:D,4,0),"") -> #REF!
A88: ZCO_IA_ABRECHNUNGSSCHEMA | B88: =VLOOKUP(A88,'Z-Programme'!$A$2:$A$650,1,FALSE) -> ZCO_IA_ABRECHNUNGSSCHEMA | C88: Abrechnungsschema in vorhandenen Aufträgen aktualisieren | D88: 1 Ausführbares Programm | E88: Grundsätzlich Nein: für keine Welle relevant | F88: Irrelevant | J88: X | K88: Nein, keine Übernahme | L88: Roland, 23.2.2024: Nein, wird nicht mehr benötigt lt. P2P-Team. | N88: =IF(#REF!="Ja",VLOOKUP(A88,'[1]ZArtefakte aus Listen'!A:B,2,0),"") -> #REF! | Q88: =IF(#REF!="Ja",VLOOKUP(A88,'[1]ZArtefakte aus Listen'!A:D,4,0),"") -> #REF!
A89: ZCO_ILV_AUSWERT | B89: =VLOOKUP(A89,'Z-Programme'!$A$2:$A$650,1,FALSE) -> ZCO_ILV_AUSWERT | C89: Abstimmung SAPCO mit Sachkonten ILV aus SAP-FI | D89: 1 Ausführbares Programm | E89: Grundsätzlich Nein: für keine Welle relevant | F89: Irrelevant | J89: X | K89: Nein, keine Übernahme | L89: Roland, 23.2.2024: Nein, wird nicht mehr benötigt lt. P2P-Team. | N89: =IF(#REF!="Ja",VLOOKUP(A89,'[1]ZArtefakte aus Listen'!A:B,2,0),"") -> #REF! | Q89: =IF(#REF!="Ja",VLOOKUP(A89,'[1]ZArtefakte aus Listen'!A:D,4,0),"") -> #REF!
A90: ZCO_ILV_AUTOMABHAK | B90: =VLOOKUP(A90,'Z-Programme'!$A$2:$A$650,1,FALSE) -> ZCO_ILV_AUTOMABHAK | C90: Programm ZCO_ILV_AUTOMABHAK | D90: 1 Ausführbares Programm | E90: Grundsätzlich Nein: für keine Welle relevant | F90: Irrelevant | J90: X | K90: Nein, keine Übernahme | L90: Roland, 23.2.2024: Nein, wird nicht mehr benötigt lt. P2P-Team. | N90: =IF(#REF!="Ja",VLOOKUP(A90,'[1]ZArtefakte aus Listen'!A:B,2,0),"") -> #REF! | Q90: =IF(#REF!="Ja",VLOOKUP(A90,'[1]ZArtefakte aus Listen'!A:D,4,0),"") -> #REF!
A91: ZCO_ILV_FI | B91: =VLOOKUP(A91,'Z-Programme'!$A$2:$A$650,1,FALSE) -> ZCO_ILV_FI | C91: Auswertung FI-Buchungen für ILV | D91: 1 Ausführbares Programm | E91: Grundsätzlich Nein: für keine Welle relevant | F91: Irrelevant | J91: X | K91: Nein, keine Übernahme | L91: Roland, 23.2.2024: Nein, wird nicht mehr benötigt lt. P2P-Team. | N91: =IF(#REF!="Ja",VLOOKUP(A91,'[1]ZArtefakte aus Listen'!A:B,2,0),"") -> #REF! | Q91: =IF(#REF!="Ja",VLOOKUP(A91,'[1]ZArtefakte aus Listen'!A:D,4,0),"") -> #REF!
A92: ZCO_ILV_KENNZAHL | B92: =VLOOKUP(A92,'Z-Programme'!$A$2:$A$650,1,FALSE) -> ZCO_ILV_KENNZAHL | C92: Programm ZCO_ILV_KENNZAHLEN | D92: 1 Ausführbares Programm | E92: tbd, (Klärung mit NTT) ob in S/4HANA anders abbildbar, sonst ja, relevant in Welle 1 | F92: P2P | J92: X | K92: Nein, keine Übernahme | L92: 17.02.25: Programm greift inzwischen auf Plan-Zahlen zu | N92: =IF(#REF!="Ja",VLOOKUP(A92,'[1]ZArtefakte aus Listen'!A:B,2,0),"") -> #REF! | Q92: =IF(#REF!="Ja",VLOOKUP(A92,'[1]ZArtefakte aus Listen'!A:D,4,0),"") -> #REF!
A93: ZCO_ILV_KONVERT | B93: =VLOOKUP(A93,'Z-Programme'!$A$2:$A$650,1,FALSE) -> ZCO_ILV_KONVERT | C93: Konvertierung ILV-Schnittstelle: Alte -> Neue Struktur | D93: 1 Ausführbares Programm | E93: Grundsätzlich Nein: für keine Welle relevant | F93: Irrelevant | J93: X | K93: Nein, keine Übernahme | L93: Roland, 23.2.2024: Nein, wird nicht mehr benötigt lt. P2P-Team. | N93: =IF(#REF!="Ja",VLOOKUP(A93,'[1]ZArtefakte aus Listen'!A:B,2,0),"") -> #REF! | Q93: =IF(#REF!="Ja",VLOOKUP(A93,'[1]ZArtefakte aus Listen'!A:D,4,0),"") -> #REF!
A94: ZCO_ILV_LIZENZVERRECHNUNG | B94: =VLOOKUP(A94,'Z-Programme'!$A$2:$A$650,1,FALSE) -> ZCO_ILV_LIZENZVERRECHNUNG | D94: 1 Ausführbares Programm | E94: tbd, (Klärung mit NTT) ob in S/4HANA anders abbildbar, sonst ja, relevant in Welle 1 | F94: Utilities Basis Lizenzverrechnung | J94: X | K94: dieser ABAP wird nicht übernommen, aber evtl. durch eine Neuprogrammeirung ersetzt (fachl. Ansprechpartner T. Heigenmoser) | L94: Roland, 23.2.2024: tbd, da abhängig vom Lizenzmodell in S/4HANA. Termin mit P2P-Team. | M94: X | N94: =IF(#REF!="Ja",VLOOKUP(A94,'[1]ZArtefakte aus Listen'!A:B,2,0),"") -> #REF! | Q94: =IF(#REF!="Ja",VLOOKUP(A94,'[1]ZArtefakte aus Listen'!A:D,4,0),"") -> #REF!
A95: ZCO_ILV_PCDATEIUEBERNAHME | B95: =VLOOKUP(A95,'Z-Programme'!$A$2:$A$650,1,FALSE) -> ZCO_ILV_PCDATEIUEBERNAHME | C95: Übernahme der Dateien für die ILV | D95: 1 Ausführbares Programm | E95: Grundsätzlich Nein: für keine Welle relevant | F95: Irrelevant | J95: X | K95: Nein, keine Übernahme | L95: Roland, 23.2.2024: Nein, wird nicht mehr benötigt lt. P2P-Team. | N95: =IF(#REF!="Ja",VLOOKUP(A95,'[1]ZArtefakte aus Listen'!A:B,2,0),"") -> #REF! | Q95: =IF(#REF!="Ja",VLOOKUP(A95,'[1]ZArtefakte aus Listen'!A:D,4,0),"") -> #REF!
A96: ZCO_ILV_POSTPROT_AKT | B96: =VLOOKUP(A96,'Z-Programme'!$A$2:$A$650,1,FALSE) -> ZCO_ILV_POSTPROT_AKT | C96: Buchungsprotokolltabelle aktualisieren | D96: 1 Ausführbares Programm | E96: Grundsätzlich Nein: für keine Welle relevant | F96: Irrelevant | J96: X | K96: Nein, keine Übernahme | L96: Roland, 23.2.2024: Nein, wird nicht mehr benötigt lt. P2P-Team. | N96: =IF(#REF!="Ja",VLOOKUP(A96,'[1]ZArtefakte aus Listen'!A:B,2,0),"") -> #REF! | Q96: =IF(#REF!="Ja",VLOOKUP(A96,'[1]ZArtefakte aus Listen'!A:D,4,0),"") -> #REF!
A97: ZCO_ILV_SAMMLER_LOESCHEN | B97: =VLOOKUP(A97,'Z-Programme'!$A$2:$A$650,1,FALSE) -> ZCO_ILV_SAMMLER_LOESCHEN | C97: Sammeldateiloeschung | D97: 1 Ausführbares Programm | E97: Grundsätzlich Nein: für keine Welle relevant | F97: Irrelevant | J97: X | K97: Nein, keine Übernahme | L97: Roland, 23.2.2024: Nein, wird nicht mehr benötigt lt. P2P-Team. | N97: =IF(#REF!="Ja",VLOOKUP(A97,'[1]ZArtefakte aus Listen'!A:B,2,0),"") -> #REF! | Q97: =IF(#REF!="Ja",VLOOKUP(A97,'[1]ZArtefakte aus Listen'!A:D,4,0),"") -> #REF!
A98: ZCO_ILV_STS | B98: =VLOOKUP(A98,'Z-Programme'!$A$2:$A$650,1,FALSE) -> ZCO_ILV_STS | C98: Programm ZCO_ILV | D98: 1 Ausführbares Programm | E98: Ja, in Welle 1 relevant | F98: P2P | J98: X | K98: Nein, keine Übernahme | L98: 17.02.25: wird nicht mehr benötigt, da alle Dateien ILV über die ILV-App laufen | N98: =IF(#REF!="Ja",VLOOKUP(A98,'[1]ZArtefakte aus Listen'!A:B,2,0),"") -> #REF! | Q98: =IF(#REF!="Ja",VLOOKUP(A98,'[1]ZArtefakte aus Listen'!A:D,4,0),"") -> #REF!
A99: ZCO_ILV_VORPROGRAMM | B99: =VLOOKUP(A99,'Z-Programme'!$A$2:$A$650,1,FALSE) -> ZCO_ILV_VORPROGRAMM | C99: Vorprogramm zur ILV | D99: 1 Ausführbares Programm | E99: Ja, in Welle 1 relevant | F99: P2P | J99: X | K99: Nein, keine Übernahme | L99: 17.02.25: wird nicht mehr benötigt, da alle Dateien ILV über die ILV-App laufen | N99: =IF(#REF!="Ja",VLOOKUP(A99,'[1]ZArtefakte aus Listen'!A:B,2,0),"") -> #REF! | Q99: =IF(#REF!="Ja",VLOOKUP(A99,'[1]ZArtefakte aus Listen'!A:D,4,0),"") -> #REF!
A100: ZCO_KALC_DRUCK | B100: =VLOOKUP(A100,'Z-Programme'!$A$2:$A$650,1,FALSE) -> ZCO_KALC_DRUCK | C100: KALC FI Belegdaten für den Druck exportieren | D100: 1 Ausführbares Programm | E100: Grundsätzlich Nein: für keine Welle relevant | F100: Irrelevant | J100: X | K100: Nein, keine Übernahme | L100: Roland, 23.2.2024: Nein, wird nicht mehr benötigt lt. P2P-Team. | N100: =IF(#REF!="Ja",VLOOKUP(A100,'[1]ZArtefakte aus Listen'!A:B,2,0),"") -> #REF! | Q100: =IF(#REF!="Ja",VLOOKUP(A100,'[1]ZArtefakte aus Listen'!A:D,4,0),"") -> #REF!
A101: ZCO_KENNZAHLEN_ABZUG | B101: =VLOOKUP(A101,'Z-Programme'!$A$2:$A$650,1,FALSE) -> ZCO_KENNZAHLEN_ABZUG | C101: Kennzahlen Abzug (Export) | D101: 1 Ausführbares Programm | E101: Ja, in Welle 1 relevant | F101: P2P | G101: KDB-Entscheidung vom 17.3.2025, Entscheidung in Realize-Phase | K101: Ja, Übernahme | L101: Lädt aus dem SAP Kennzahlen, z.B. Umsätze (Folgeschritt, siehe ZCO_Kennzahlen_Import); 17.02.25: wird prozessual für die Umlagen weiterhin benötigt, da oft Einfrierung von Plan-Stand | M101: in CALM anzulegen | N101: =IF(#REF!="Ja",VLOOKUP(A101,'[1]ZArtefakte aus Listen'!A:B,2,0),"") -> #REF! | Q101: =IF(#REF!="Ja",VLOOKUP(A101,'[1]ZArtefakte aus Listen'!A:D,4,0),"") -> #REF!
A102: ZCO_KENNZAHLEN_IMPORT | B102: =VLOOKUP(A102,'Z-Programme'!$A$2:$A$650,1,FALSE) -> ZCO_KENNZAHLEN_IMPORT | C102: Kennzahlen Istschnittstelle Import | D102: 1 Ausführbares Programm | E102: Ja, in Welle 1 relevant | F102: P2P | G102: KDB-Entscheidung vom 17.3.2025, Entscheidung in Realize-Phase | K102: Ja, Übernahme | L102: Spielt Kennzahlen ins SAP, z.B. Umsätze die davor aus den KOA-Gruppen ermittelt wurden (siehe ZCO_Kennzahlen_Abzug); 17.02.25: wird prozessual für die Umlagen weiterhin benötigt, da oft Einfrierung von Plan-Stand | M102: in CALM anzulegen | N102: =IF(#REF!="Ja",VLOOKUP(A102,'[1]ZArtefakte aus Listen'!A:B,2,0),"") -> #REF! | Q102: =IF(#REF!="Ja",VLOOKUP(A102,'[1]ZArtefakte aus Listen'!A:D,4,0),"") -> #REF!
A103: ZCO_KENNZAHLEN_START | B103: =VLOOKUP(A103,'Z-Programme'!$A$2:$A$650,1,FALSE) -> ZCO_KENNZAHLEN_START | C103: Programm ZCO_KENNZAHLEN_START | D103: 1 Ausführbares Programm | E103: Grundsätzlich Nein: für keine Welle relevant | F103: Irrelevant | J103: X | K103: Nein, keine Übernahme | L103: Roland, 23.2.2024: Nein, wird nicht mehr benötigt lt. P2P-Team. | N103: =IF(#REF!="Ja",VLOOKUP(A103,'[1]ZArtefakte aus Listen'!A:B,2,0),"") -> #REF! | Q103: =IF(#REF!="Ja",VLOOKUP(A103,'[1]ZArtefakte aus Listen'!A:D,4,0),"") -> #REF!
A104: ZCO_KOSTENARTEN_ERGRE | B104: =VLOOKUP(A104,'Z-Programme'!$A$2:$A$650,1,FALSE) -> ZCO_KOSTENARTEN_ERGRE | C104: Kostenarten und Kostenartengruppen | D104: 1 Ausführbares Programm | E104: Grundsätzlich Nein: für keine Welle relevant | F104: Irrelevant | J104: X | K104: Nein, keine Übernahme | L104: Roland, 23.2.2024: Nein, wird nicht mehr benötigt lt. P2P-Team. | N104: =IF(#REF!="Ja",VLOOKUP(A104,'[1]ZArtefakte aus Listen'!A:B,2,0),"") -> #REF! | Q104: =IF(#REF!="Ja",VLOOKUP(A104,'[1]ZArtefakte aus Listen'!A:D,4,0),"") -> #REF!
A105: ZCO_KOSTENSTELLENEXPORT | B105: =VLOOKUP(A105,'Z-Programme'!$A$2:$A$650,1,FALSE) -> ZCO_KOSTENSTELLENEXPORT | C105: Auftrag- und Kostenstellenstammdaten: SQL-DB, TERMIKON, RACF, IBLA. | D105: 1 Ausführbares Programm | E105: Grundsätzlich Nein: für keine Welle relevant | F105: Irrelevant | J105: X | K105: Nein, keine Übernahme | L105: Roland, 23.2.2024: Nein, wird nicht mehr benötigt lt. P2P-Team. | N105: =IF(#REF!="Ja",VLOOKUP(A105,'[1]ZArtefakte aus Listen'!A:B,2,0),"") -> #REF! | Q105: =IF(#REF!="Ja",VLOOKUP(A105,'[1]ZArtefakte aus Listen'!A:D,4,0),"") -> #REF!
A106: ZCO_KSTABZUG_AVM | B106: =VLOOKUP(A106,'Z-Programme'!$A$2:$A$650,1,FALSE) -> ZCO_KSTABZUG_AVM | C106: Kostenstellenabzug für AVM | D106: 1 Ausführbares Programm | E106: Grundsätzlich Nein: für keine Welle relevant | F106: Irrelevant | J106: X | K106: Nein, keine Übernahme | L106: 19.02. ist bereits jetzt im R/3 abgeschaltet | N106: =IF(#REF!="Ja",VLOOKUP(A106,'[1]ZArtefakte aus Listen'!A:B,2,0),"") -> #REF! | Q106: =IF(#REF!="Ja",VLOOKUP(A106,'[1]ZArtefakte aus Listen'!A:D,4,0),"") -> #REF!
A107: ZCO_KSTABZUG_LOGA | B107: =VLOOKUP(A107,'Z-Programme'!$A$2:$A$650,1,FALSE) -> ZCO_KSTABZUG_LOGA | C107: Kostenstellenabzug für Loga | D107: 1 Ausführbares Programm | E107: Grundsätzlich Nein: für keine Welle relevant | F107: Irrelevant | J107: X | K107: Nein, keine Übernahme | L107: Roland, 13.11.2023: Nein, Loga wird durch HCM abgelöst | N107: =IF(#REF!="Ja",VLOOKUP(A107,'[1]ZArtefakte aus Listen'!A:B,2,0),"") -> #REF! | Q107: =IF(#REF!="Ja",VLOOKUP(A107,'[1]ZArtefakte aus Listen'!A:D,4,0),"") -> #REF!
...

Sheet CALM
A1: USR | B1: Status | C1: Timebox
A2: DEV-005 | B2: Nicht relevant | C2: Realize W1 | D2: S2P
A3: DEV-008 | B3: Nicht relevant | C3: Realize W1 | D3: S2P
A4: DEV-010 | B4: In Bearbeitung | C4: Realize W1 | D4: S2P | E4: =VLOOKUP(A4,'Z-Programme'!#REF!,1,FALSE) -> #REF!
A5: DEV-003 | B5: Nicht relevant | C5: Realize W1 | D5: R2R
A6: DEV-012 | B6: Nicht relevant | C6: MS-Entwicklungsphase 2 | D6: S2P
A7: DEV-014 | B7: Nicht relevant | C7: MS-Entwicklungsphase 3 | D7: I2C
A8: DEV-016 | B8: Nicht relevant | C8: MS-Entwicklungsphase 3 | D8: I2C
A9: DEV-021 | B9: In Bearbeitung | C9: Realize W1 | D9: I2C
A10: DEV-025 | B10: In Bearbeitung | C10: Realize W1 | D10: I2C | E10: =VLOOKUP(A10,'Z-Programme'!#REF!,1,FALSE) -> #REF!
A11: DEV-033 | B11: In Bearbeitung | C11: MS-Entwicklungsphase 2 | D11: I2C | E11: =VLOOKUP(A11,'Z-Programme'!#REF!,1,FALSE) -> #REF!
A12: DEV-034 | B12: Nicht relevant | C12: MS-Entwicklungsphase 2 | D12: I2C | E12: =VLOOKUP(A12,'Z-Programme'!#REF!,1,FALSE) -> #REF!
A13: DEV-035 | B13: In Bearbeitung | C13: MS-Entwicklungsphase 2 | D13: I2C | E13: =VLOOKUP(A13,'Z-Programme'!#REF!,1,FALSE) -> #REF!
A14: DEV-036 | B14: Nicht relevant | C14: MS-Entwicklungsphase 2 | D14: I2C
A15: DEV-037 | B15: Gesperrt | C15: MS-Entwicklungsphase 2 | D15: I2C | E15: =VLOOKUP(A15,'Z-Programme'!#REF!,1,FALSE) -> #REF!
A16: DEV-038 | B16: Nicht relevant | C16: MS-Entwicklungsphase 2 | D16: I2C | E16: =VLOOKUP(A16,'Z-Programme'!#REF!,1,FALSE) -> #REF!
A17: DEV-039 | B17: Nicht relevant | C17: MS-Entwicklungsphase 2 | D17: I2C | E17: =VLOOKUP(A17,'Z-Programme'!#REF!,1,FALSE) -> #REF!
A18: DEV-040 | B18: Nicht relevant | C18: MS-Entwicklungsphase 2 | D18: I2C | E18: =VLOOKUP(A18,'Z-Programme'!#REF!,1,FALSE) -> #REF!
A19: DEV-041 | B19: Nicht relevant | C19: MS-Entwicklungsphase 2 | D19: I2C | E19: =VLOOKUP(A19,'Z-Programme'!#REF!,1,FALSE) -> #REF!
A20: DEV-042 | B20: Nicht relevant | C20: Realize W1 | D20: I2C
A21: DEV-048 | B21: Nicht relevant | C21: Realize W1 | D21: R2R
A22: DEV-049 | B22: Nicht relevant | C22: Realize W1 | D22: R2R
A23: DEV-054 | B23: Nicht relevant | C23: Realize W1 | D23: R2R
A24: DEV-050 | B24: Nicht relevant | C24: Realize W1 | D24: I2C
A25: DEV-051 | B25: Nicht relevant | C25: Realize W1 | D25: I2C
A26: DEV-053 | B26: In Bearbeitung | C26: Realize W1 | D26: I2C | E26: =VLOOKUP(A26,'Z-Programme'!#REF!,1,FALSE) -> #REF!
A27: DEV-056 | B27: Fertig | C27: Realize W1 | D27: P2P
A28: DEV-057 | B28: Fertig | C28: Realize W1 | D28: P2P
A29: DEV-058 | B29: Fertig | C29: Realize W1 | D29: P2P
A30: DEV-059 | B30: Fertig | C30: Realize W1 | D30: P2P
A31: DEV-094 | B31: Nicht relevant | C31: MS-Entwicklungsphase 3 | D31: Tax
A32: DEV-095 | B32: Fertig | C32: Realize W1 | D32: P2P
A33: DEV-096 | B33: Fertig | C33: Realize W1 | D33: P2P
A34: DEV-061 | B34: Nicht relevant | C34: MS-Entwicklungsphase 3 | D34: S2P
A35: DEV-062 | B35: Nicht relevant | C35: MS-Entwicklungsphase 3 | D35: XX
A36: DEV-066 | B36: Nicht relevant | C36: MS-Entwicklungsphase 3 | D36: S2P
A37: DEV-067 | B37: In Bearbeitung | C37: Realize W1 | D37: S2P | E37: =VLOOKUP(A37,'Z-Programme'!#REF!,1,FALSE) -> #REF!
A38: DEV-068 | B38: In Bearbeitung | C38: Realize W1 | D38: I2C | E38: =VLOOKUP(A38,'Z-Programme'!#REF!,1,FALSE) -> #REF!
A39: DEV-070 | B39: In Bearbeitung | C39: Realize W1 | D39: S2P | E39: =VLOOKUP(A39,'Z-Programme'!#REF!,1,FALSE) -> #REF!
A40: DEV-072 | B40: In Bearbeitung | C40: Realize W1 | D40: S2P | E40: =VLOOKUP(A40,'Z-Programme'!#REF!,1,FALSE) -> #REF!
A41: DEV-073 | B41: In Bearbeitung | C41: Realize W1 | D41: P2P | E41: =VLOOKUP(A41,'Z-Programme'!#REF!,1,FALSE) -> #REF!
A42: DEV-074 | B42: Nicht relevant | C42: MS-Entwicklungsphase 3 | D42: S2P
A43: DEV-075 | B43: Nicht relevant | C43: MS-Entwicklungsphase 3 | D43: XAP
A44: DEV-079 | B44: In Bearbeitung | C44: Realize W1 | D44: I2C | E44: =VLOOKUP(A44,'Z-Programme'!#REF!,1,FALSE) -> #REF!
A45: DEV-081 | B45: Fertig | C45: Realize W1 | D45: I2C | E45: =VLOOKUP(A45,'Z-Programme'!#REF!,1,FALSE) -> #REF!
A46: DEV-082 | B46: In Bearbeitung | C46: Realize W1 | D46: XAP | E46: =VLOOKUP(A46,'Z-Programme'!#REF!,1,FALSE) -> #REF!
A47: DEV-083 | B47: In Bearbeitung | C47: Realize W1 | D47: R2R | E47: =VLOOKUP(A47,'Z-Programme'!#REF!,1,FALSE) -> #REF!
A48: DEV-084 | B48: In Bearbeitung | C48: Realize W1 | D48: S2P | E48: =VLOOKUP(A48,'Z-Programme'!#REF!,1,FALSE) -> #REF!
A49: DEV-086 | B49: Nicht relevant | C49: MS-Entwicklungsphase 3 | D49: I2C
A50: DEV-087 | B50: In Bearbeitung | C50: Realize W1 | D50: R2R | E50: =VLOOKUP(A50,'Z-Programme'!#REF!,1,FALSE) -> #REF!
A51: DEV-089 | B51: In Bearbeitung | C51: Realize W1 | D51: S2P | E51: =VLOOKUP(A51,'Z-Programme'!#REF!,1,FALSE) -> #REF!
A52: DEV-090 | B52: Nicht relevant | C52: MS-Entwicklungsphase 3 | D52: R2R
A53: DEV-092 | B53: Nicht relevant | C53: MS-Entwicklungsphase 3 | D53: R2R | E53: =VLOOKUP(A53,'Z-Programme'!#REF!,1,FALSE) -> #REF!
A54: DEV-093 | B54: Nicht relevant | C54: MS-Entwicklungsphase 3 | D54: I2C
A55: DEV-080 | B55: In Bearbeitung | C55: Realize W1 | D55: I2C | E55: =VLOOKUP(A55,'Z-Programme'!#REF!,1,FALSE) -> #REF!
A56: DEV-071 | B56: In Bearbeitung | C56: MS-Entwicklungsphase 3 | D56: S2P | E56: =VLOOKUP(A56,'Z-Programme'!#REF!,1,FALSE) -> #REF!
A57: DEV-060 | B57: Nicht relevant | C57: MS-Entwicklungsphase 1 | D57: I2C
A58: DEV-099 | B58: Fertig | C58: Realize W1 | D58: P2P
A59: DEV-064 | B59: In Bearbeitung | C59: Realize W1 | D59: S2P | E59: =VLOOKUP(A59,'Z-Programme'!#REF!,1,FALSE) -> #REF!
A60: DEV-101 | B60: Fertig | C60: Realize W1 | D60: P2P
A61: DEV-102 | B61: Fertig | C61: Realize W1 | D61: PSP
A62: DEV-097 | B62: Nicht relevant | C62: MS-Entwicklungsphase 3 | D62: S2P
A63: DEV-098 | B63: Nicht relevant | C63: MS-Entwicklungsphase 3 | D63: S2P
A64: DEV-103 | B64: Nicht relevant | C64: Iteration 3 (W1) | D64: A2R-02.01
A65: DEV-104 | B65: Offen | C65: Realize W2 | D65: I2C | E65: =VLOOKUP(A65,'Z-Programme'!#REF!,1,FALSE) -> #REF!
A66: DEV-105 | B66: In Bearbeitung | C66: Realize W1 | D66: S2P | E66: =VLOOKUP(A66,'Z-Programme'!#REF!,1,FALSE) -> #REF!
A67: DEV-108 | B67: In Bearbeitung | C67: Realize W1 | D67: I2C | E67: =VLOOKUP(A67,'Z-Programme'!#REF!,1,FALSE) -> #REF!
A68: DEV-109 | B68: Nicht relevant | C68: Iteration 3 (W1) | D68: P2P
A69: DEV-110 | B69: Nicht relevant | C69: Iteration 3 (W1) | D69: P2P
A70: DEV-111 | B70: Nicht relevant | C70: Iteration 3 (W1) | D70: P2P
A71: DEV-112 | B71: Nicht relevant | C71: Iteration 3 (W1) | D71: P2P
A72: DEV-113 | B72: Nicht relevant | C72: Realize W1 | D72: P2P | E72: =VLOOKUP(A72,'Z-Programme'!#REF!,1,FALSE) -> #REF!
A73: DEV-114 | B73: In Bearbeitung | C73: Realize W1 | D73: P2P | E73: =VLOOKUP(A73,'Z-Programme'!#REF!,1,FALSE) -> #REF!
A74: DEV-115 | B74: Nicht relevant | C74: Iteration 3 (W1) | D74: P2P
A75: DEV-116 | B75: Nicht relevant | C75: Iteration 3 (W1) | D75: P2P
A76: DEV-117 | B76: Nicht relevant | C76: Iteration 3 (W1) | D76: Tax
A77: DEV-118 | B77: In Bearbeitung | C77: Realize W1 | D77: P2P | E77: =VLOOKUP(A77,'Z-Programme'!#REF!,1,FALSE) -> #REF!
A78: DEV-119 | B78: In Bearbeitung | C78: Realize W1 | D78: R2R | E78: =VLOOKUP(A78,'Z-Programme'!#REF!,1,FALSE) -> #REF!
A79: DEV-120 | B79: Offen | C79: Realize W2 | D79: R2R | E79: =VLOOKUP(A79,'Z-Programme'!#REF!,1,FALSE) -> #REF!
A80: DEV-121 | B80: Fertig | C80: Realize W1 | D80: I2C | E80: =VLOOKUP(A80,'Z-Programme'!#REF!,1,FALSE) -> #REF!
A81: DEV-122 | B81: Nicht relevant | C81: Iteration 3 (W1) | D81: R2R
A82: DEV-123 | B82: Nicht relevant | C82: Iteration 3 (W1) | D82: R2R
A83: DEV-124 | B83: In Bearbeitung | C83: Realize W1 | D83: I2C | E83: =VLOOKUP(A83,'Z-Programme'!#REF!,1,FALSE) -> #REF!
A84: DEV-125 | B84: Offen | C84: Realize W2 | D84: R2R | E84: =VLOOKUP(A84,'Z-Programme'!#REF!,1,FALSE) -> #REF!
A85: DEV-126 | B85: Nicht relevant | C85: 2. Integrationstest (W1) | D85: R2R
A86: DEV-127 | B86: Offen | C86: Realize W2 | D86: Treasury | E86: =VLOOKUP(A86,'Z-Programme'!#REF!,1,FALSE) -> #REF!
A87: DEV-128 | B87: In Bearbeitung | C87: Realize W1 | D87: S2P | E87: =VLOOKUP(A87,'Z-Programme'!#REF!,1,FALSE) -> #REF!
A88: DEV-130 | B88: Offen | C88: Realize W2 | D88: R2R | E88: =VLOOKUP(A88,'Z-Programme'!#REF!,1,FALSE) -> #REF!
A89: DEV-129 | B89: Offen | C89: Realize W2 | D89: Entwicklung | E89: =VLOOKUP(A89,'Z-Programme'!#REF!,1,FALSE) -> #REF!
A90: DEV-131 | B90: Offen | C90: Realize W2 | D90: Treasury | E90: =VLOOKUP(A90,'Z-Programme'!#REF!,1,FALSE) -> #REF!
A91: DEV-132 | B91: Gesperrt | C91: Iteration 3 (W1) | D91: I2C | E91: =VLOOKUP(A91,'Z-Programme'!#REF!,1,FALSE) -> #REF!
A92: DEV-133 | B92: Offen | C92: Realize W2 | D92: P2R | E92: =VLOOKUP(A92,'Z-Programme'!#REF!,1,FALSE) -> #REF!
A93: DEV-134 | B93: In Bearbeitung | C93: Realize W1 | D93: S2P | E93: =VLOOKUP(A93,'Z-Programme'!#REF!,1,FALSE) -> #REF!
A94: DEV-135 | B94: Nicht relevant | C94: Iteration 3 (W1) | D94: Entwicklung
A95: DEV-136 | B95: Offen | C95: Realize W2 | D95: I2C | E95: =VLOOKUP(A95,'Z-Programme'!#REF!,1,FALSE) -> #REF!
A96: DEV-137 | B96: Nicht relevant | C96: Iteration 3 (W1) | D96: Entwicklung
A97: DEV-138 | B97: Gesperrt | C97: Iteration 3 (W1) | D97: TRM | E97: =VLOOKUP(A97,'Z-Programme'!#REF!,1,FALSE) -> #REF!
A98: DEV-139 | B98: Nicht relevant | C98: Iteration 3 (W1) | D98: Entwicklung
A99: DEV-140 | B99: Gesperrt | C99: Iteration 3 (W1) | D99: TRM
A100: DEV-141 | B100: Nicht relevant | C100: Iteration 3 (W1) | D100: TRM
...

Sheet USR mit Z-Artefakt
A1: USR | B1: Z-Programm | C1: Match
A2: DEV-005 | B2: Nein | C2: =VLOOKUP(A2,'Z-Programme'!#REF!,1,FALSE) -> #REF!
A3: DEV-008 | B3: Nein | C3: =VLOOKUP(A3,'Z-Programme'!#REF!,1,FALSE) -> #REF!
A4: DEV-010 | B4: Ja | C4: =VLOOKUP(A4,'Z-Programme'!#REF!,1,FALSE) -> #REF!
A5: DEV-003 | B5: Nein | C5: =VLOOKUP(A5,'Z-Programme'!#REF!,1,FALSE) -> #REF!
A6: DEV-012 | B6: Ja | C6: =VLOOKUP(A6,'Z-Programme'!#REF!,1,FALSE) -> #REF!
A7: DEV-014 | B7: Nein | C7: =VLOOKUP(A7,'Z-Programme'!#REF!,1,FALSE) -> #REF!
A8: DEV-016 | B8: Nein | C8: =VLOOKUP(A8,'Z-Programme'!#REF!,1,FALSE) -> #REF!
A9: DEV-021 | B9: Nein | C9: =VLOOKUP(A9,'Z-Programme'!#REF!,1,FALSE) -> #REF!
A10: DEV-025 | B10: Ja | C10: =VLOOKUP(A10,'Z-Programme'!#REF!,1,FALSE) -> #REF!
A11: DEV-033 | B11: Ja | C11: =VLOOKUP(A11,'Z-Programme'!#REF!,1,FALSE) -> #REF!
A12: DEV-034 | B12: Ja | C12: =VLOOKUP(A12,'Z-Programme'!#REF!,1,FALSE) -> #REF!
A13: DEV-035 | B13: Ja | C13: =VLOOKUP(A13,'Z-Programme'!#REF!,1,FALSE) -> #REF!
... A120: DEV-053 | B120: Nein | C120: =VLOOKUP(A120,'Z-Programme'!#REF!,1,FALSE) -> #REF!
A121: DEV-053 | B121: Nein | C121: =VLOOKUP(A121,'Z-Programme'!#REF!,1,FALSE) -> #REF! | R121: Fracht
A122: DEV-053 | B122: Nein | C122: =VLOOKUP(A122,'Z-Programme'!#REF!,1,FALSE) -> #REF!
A123: DEV-053 | B123: Nein | C123: =VLOOKUP(A123,'Z-Programme'!#REF!,1,FALSE) -> #REF!
A124: DEV-053 | B124: Nein | C124: =VLOOKUP(A124,'Z-Programme'!#REF!,1,FALSE) -> #REF!
A125: DEV-053 | B125: Nein | C125: =VLOOKUP(A125,'Z-Programme'!#REF!,1,FALSE) -> #REF!
A126: DEV-053 | B126: Nein | C126: =VLOOKUP(A126,'Z-Programme'!#REF!,1,FALSE) -> #REF!
A127: DEV-053 | B127: Nein | C127: =VLOOKUP(A127,'Z-Programme'!#REF!,1,FALSE) -> #REF!
A128: DEV-053 | B128: Nein | C128: =VLOOKUP(A128,'Z-Programme'!#REF!,1,FALSE) -> #REF!
A129: DEV-053 | B129: Nein | C129: =VLOOKUP(A129,'Z-Programme'!#REF!,1,FALSE) -> #REF!
A130: DEV-053 | B130: Nein | C130: =VLOOKUP(A130,'Z-Programme'!#REF!,1,FALSE) -> #REF!
A131: DEV-079 | B131: Nein | C131: =VLOOKUP(A131,'Z-Programme'!#REF!,1,FALSE) -> #REF!
A132: DEV-156 | B132: Nein | C132: =VLOOKUP(A132,'Z-Programme'!#REF!,1,FALSE) -> #REF!
A133: DEV-157 | B133: Nein | C133: =VLOOKUP(A133,'Z-Programme'!#REF!,1,FALSE) -> #REF!
... A189: DEV-002 | B189: Ja | C189: =VLOOKUP(A189,'Z-Programme'!#REF!,1,FALSE) -> #REF!

Sheet sbbnv temp d010sinf
A1: 1 | B1: 2 | C1: 3 | D1: 4 | E1: 5 | F1: 6 | G1: 7 | H1: 8 | I1: 9 | J1: 10 | K1: 11 | L1: 12 | M1: 13 | N1: 14 | O1: 15 | P1: 16 | Q1: 17 | R1: 18 | S1: 19 | T1: 20
A2: PROG | B2: R3STATE | C2: SQLX | D2: EDTX | E2: DBNA | F2: CLAS | G2: TYPE | H2: OCCURS | I2: SUBC | J2: APPL | K2: SECU | L2: CNAM | M2: CDAT | N2: VERN | O2: LEVL | P2: RSTAT | Q2: RMAND | R2: RLOAD | S2: UNAM | U2: UDAT | V2: UTIME | W2: DATALG | X2: VARCL | Y2: DBAPL | Z2: FIXPT | AA2: SSET | AB2: SDATE | AC2: STIME | AD2: IDATE | AE2: ITIME | AF2: LDBNAME | AG2: UCCHECK | AH2: MAXLINELN
A3: ZFI_LAVA01 | B3: A | I3: 1 | J3: F | L3: ITTEXUI | M3: 45749 | N3: 000010 | P3: K | Q3: 100 | R3: DE | S3: ITTEXUI | T3: Irina Ultschenko | U3: 45925 | V3: 0.45231481 | W3: 57879 | X3: X | Z3: X | AB3: 45951 | AC3: 163835 | AD3: 45925 | AE3: 105120 | AG3: X | AH3: 0
A4: ZFI_SEPA_PRENOTE_INCL | B4: A | I4: I | J4: F | L4: ITTEXKA | M4: 45525 | N4: 000011 | P4: K | Q4: 100 | R4: DE | S4: ITTEXKA | T4: Alexander Krawietz | U4: 45525 | V4: 0.30334491 | W4: 4210 | X4: X | AB4: 45525 | AC4: 071649 | AD4: 45525 | AE4: 071649 | AG4: X | AH4: 0
A5: ZFI_SS_FB0100 | B5: A | I5: 1 | J5: F | L5: ITTEXRM | M5: 45756 | N5: 000028 | P5: K | Q5: 100 | R5: DE | S5: ITTEXRM | T5: Mayrina Rud | U5: 45945 | V5: 0.74018519 | W5: 44018 | X5: X | AB5: 45945 | AC5: 174552 | AD5: 45945 | AE5: 174552 | AG5: X | AH5: 0
A6: ZMV45AFZZ_SAVE_DOCUMENT_PREPAR | B6: A | I6: I | J6: V | L6: ITTEXRA | M6: 45706 | N6: 000033 | P6: K | Q6: 100 | R6: DE | S6: ITTEXRA | T6: Andreas Rustemeier | U6: 45749 | V6: 0.453125 | W6: 16569 | X6: X | AB6: 45749 | AC6: 105230 | AD6: 45749 | AE6: 105230 | AG6: X | AH6: 0
A7: ZSD_ADIN01_EXIT | B7: A | I7: I | J7: V | L7: ITTEXRM | M7: 45506 | N7: 000012 | P7: P | Q7: 100 | R7: DE | S7: ITTEXWR | T7: Rolf Winter | U7: 45796 | V7: 0.48186343 | W7: 33811 | X7: X | AB7: 45796 | AC7: 113353 | AD7: 45796 | AE7: 113353 | AG7: X | AH7: 0
A8: ZSD_MAR_BASIS | B8: A | I8: 1 | J8: V | L8: ITTEXRA | M8: 45602 | N8: 000029 | P8: K | Q8: 100 | R8: DE | S8: SBBNV | T8: Andreas Rustemeier | U8: 45901 | V8: 0.73578704 | W8: 59615 | X8: X | Z8: X | AB8: 45958 | AC8: 101336 | AD8: 45901 | AE8: 173932 | AG8: X | AH8: 0
A9: ZSD_MAR_BELEGHIS | B9: A | I9: 1 | J9: V | L9: ITTEXRA | M9: 45603 | N9: 000020 | P9: K | Q9: 100 | R9: DE | S9: ITTEXRA | T9: Andreas Rustemeier | U9: 45840 | V9: 0.66013889 | W9: 17674 | X9: X | Z9: X | AB9: 45947 | AC9: 145217 | AD9: 45840 | AE9: 155036 | AG9: X | AH9: 0
A10: ZSD_MAR_FI | B10: A | I10: 1 | J10: V | L10: ITTEXRA | M10: 45609 | N10: 000013 | P10: K | Q10: 100 | R10: DE | S10: ITTEXRA | T10: Andreas Rustemeier | U10: 45680 | V10: 0.42400463 | W10: 4483 | X10: X | Z10: X | AB10: 45947 | AC10: 145217 | AD10: 45680 | AE10: 101034 | AG10: X | AH10: 0
A11: ZXVVFU02 | B11: A | I11: I | J11: S | L11: ITTEXRA | M11: 45812 | N11: 000016 | P11: T | Q11: 100 | R11: DE | S11: ITTEXRA | T11: Andreas Rustemeier | U11: 45945 | V11: 0.67263889 | W11: 6358 | X11: X | AB11: 45945 | AC11: 160836 | AD11: 45945 | AE11: 160836 | AG11: X | AH11: 0

Sheet Z-EQA300
A2: Programm | B2: Report-Titel
A3: ZFI_RFBILA00 | B3: Bilanz/GuV
A4: ZMM_IVALUA_QUEUE_DISPLAY
A5: ZMM_IVALUA_QUEUE_PROCESS
A6: ZFI_ANZ_REISE_PBS | B6: Anzahl Reisen für interne Leistungsverrechnung
A7: ZFI_SAPF150D2 | B7: FI Mahnen - Druckprogramm
A8: ZFI_EXCEL_UPLOAD | B8: Programm ZFI_EXCEL_UPLOAD
A9: ZFI_INKO00 | B9: Übergabe Inkassounternehmen - Mahndaten säumiger Zahler
A10: ZFI_INKO00_EOS | B10: EOS : Übergabe mit neuer Struktur
A11: ZFI_INKO03 | B11: Rückmeldeverarbeitung der Aktenzeichen
A12: ZFI_INKO03_EOS | B12: Rückmeldeverarbeitung der Inkassonummer
A13: ZFI_INKO04 | B13: BI: Rückmeldung Aktenzeichen: Update Debitoren Stammsatz
A14: ZFI_INKO04_EOS | B14: BI: Rückmeldung Aktenzeichen: Update Debitoren Stammsatz
A15: ZFI_INKO05 | B15: BI: belegen Segmenttext mit Aktenkennzeichen
A16: ZFI_INKO05_EOS | B16: BI: belegen Segmenttext mit Aktenkennzeichen
A17: ZFI_UPDATE_COCKPIT_ZAHLUNG | B17: Aktualisierung Tabelle ZFI_INKO_COCKPIT,ZFI_INKO_COCKPI2 für Zahlung
... A147: ZFI_ELSY_SCHNITTSTELLE | B147: Rechnungen Telekom Datenverkehr (ELSY) Konvertierung Inhouseformat
A148: Z_ACAC_D_TRANS_EXAMPLE_S4_TOP
A149: ZACAC_DATA_TRANSFER | B149: Übernahme von Debitoren-/Kreditorenrechnungen in die Accrual Engine
A150: ZFI_MONATSABSCHLUSS_UPLOAD | B150: Programm ZFI_MONATSABSCHLUSS_UPLOAD
A151: Z_ACAC_D_TRANS_EXAMPLE_S4 | B151: Übernahme von Debitoren-/Kreditorenrechnungen in die Accrual Engine
A152: ZBC_TAB_EXPIMP2 | B152: ZBC_TAB_EXPIMP2 Tabellen Impotieren, DS-Filtern, Werte-Umschlüsseln
A153: ZBC_TAB_EXPIMP2_SIK | B153: ZBC_TAB_EXPIMP2 Tabellen Impotieren, DS-Filtern ## Sicherung ###
A154: ZFI_AVM_VERSICHERUNG | B154: Umbuchung Zahlungseingänge für Versicherungsfälle Autovermietung
A155: ZFI_SAM_VBR_LISTE | B155: Sanktionsprüfung: Auswertung für Versicherungen (VBR)
A156: ZADAC_CLASSIC_TR_LAVA_EXP | B156: LAVA FX-Export
A157: ZFI_SD_UM | B157: Umbuchungen von Erlösbuchungen
A158: ZFI_SS_FB0100 | B158: Standardschnittstelle für Belegerfassung und Stammsatzpflege
A159: ZHR_CONCUR_RESET_POSTING | B159: Concur - gebuchte Expense Reports für erneute Buchung zurücksetzen
A160: ZFI_BARCO_DEL | B160: Barcodes löschen
... A211: ZFI_FILE_FOR_ABSTIMMTOOL | B211: Datei für Abstimmtool erzeugen

Sheet Tabelle1
B2: Welle 1 | C2: Welle 2 | D2: Welle 3 ff
B3: Ja | D3: Ja Ergebnis | E3: (Leer) | Q3: (Leer) Ergebnis | R3: Gesamtergebnis
B4: (Leer) | C4: (Leer) Ergebnis | E4: ? | F4: ? Ergebnis | G4: Ja | H4: Ja Ergebnis | I4: Nein | K4: Nein Ergebnis | L4: Nein | M4: Nein Ergebnis | N4: (Leer) | P4: (Leer) Ergebnis
B5: (Leer) | E5: ? | G5: Nein | I5: ? | J5: Ja | L5: Ja | N5: x | O5: (Leer)
A6: Anzahl von Z-Programm R/3 (insgesamt 654) | B6: 198 | C6: 198 | D6: 198 | E6: 29 | F6: 29 | G6: 20 | H6: 20 | I6: 38 | J6: 14 | K6: 52 | L6: 3 | M6: 3 | N6: 30 | O6: 328 | P6: 358 | Q6: 462 | R6: 660

Sheet Tabelle2
A2: Übernahme in S/4 geplant | B2: Anzahl von Übernahme in S/4 geplant
A3: Nein | B3: 328
A4: Ja | B4: 265
A5: Offen | B5: 67
A6: Gesamtergebnis | B6: 660

Sheet Z-Programme (2)
A1: Z-Programm R/3 (insgesamt 654) | B1: vorhanden EQA | C1: Übernahme in S/4 geplant | D1: USR CALM | E1: Welle 1 | F1: Welle 2 | G1: Welle 3 ff | H1: Coding Zahlwege | I1: Klärung durch | J1: Beschreibung
A2: Z_CLEAN_EVTTAB | B2: Nein | C2: Nein | J2: Hilfsprogramm zur Bereinigung Inkonsistenzen in Jobtabelle BTCEVTJOB
A3: Z_IDOC_STATUS_SET | B3: Nein | C3: Ja | F3: Nein | G3: Ja | J3: Idoc Status auf erledigt setzen (nur BuKrs 1000)
A4: Z_INFO_PRICING_SERVICES_USER | B4: Nein | C4: Nein | J4: Z_INFO_PRICING_SERVICES_USER lt. SAP Hinweis 1786263
A5: Z_REPAIR_ADRNR_1 | B5: Nein | C5: Nein | J5: Reparatur der Adressinkonsistenz in Tabelle VBPA und KNA1
A6: Z_SAPMZSWA | B6: Nein | C6: Ja | F6: Nein | G6: Ja | J6: Programm SAPMZSWA - Batterieservice
A7: Z_SAPMZSWA_MENUE | B7: Nein | C7: Ja | F7: Nein | G7: Ja | J7: Menü Batterieservice
A8: Z_SAPMZSWAT | B8: Nein | C8: Ja | F8: Nein | G8: Ja | J8: Modulpool: Elektronisches Bezahlen SWA-Terminal (Straßenwacht)
A9: Z0SAP_12 | B9: Nein | C9: Nein | J9: Datendatei-View: Geplante Abschreibungen auf Anlagen
A10: ZAA_ANLAGENTR_COPY_LANGTEXT | B10: Nein | C10: Nein | J10: Anlagentransfer Langtexte kopieren
A11: ZAA_ANLAGENTRANSFER | B11: Nein | C11: Nein | J11: Anlagentransfer
A12: ZAA_CO_KONTIERUNG | B12: Nein | C12: Nein | J12: Änderung von Innenaufträgen/Kostenstellen in Anlagen
A13: ZAA_INVE01 | B13: Nein | C13: Nein | J13: Inventurliste nach Anlagennummern / Anlagentext
A14: ZAA_INVE06 | B14: Nein | C14: Nein | J14: Inventurliste nach Anlagennummern / Anlagentext
A15: ZAA_INVE07 | B15: Nein | C15: Nein | J15: Inventurliste nach Kostenrechnungsobjekten
A16: ZAA_MASS_DOWN | B16: Nein | C16: Nein | D16: DEV-002 | J16: Anlagenstamm Massenänderung: Download
A17: ZAA_MASS_UP | B17: Nein | C17: Nein | D17: DEV-002 | J17: Massenänderung Anlagenstamm: Upload CSV-Datei
A18: ZAA_RAHIST01 | B18: Nein | C18: Nein | J18: Anlagenhistorie
A19: ZAA_RAPOST2010 | B19: Nein | C19: Nein | J19: Buchen der Abschreibungen
A20: ZAA_STAMMDAT_ALV | B20: Nein | C20: Nein | D20: DEV-002 | J20: Stammdaten-Auswertung ALV-Liste ( mehrzeilig )
A21: ZACAC_DATA_TRANSFER | B21: Ja | C21: Ja | D21: DEV-150 | E21: Ja | J21: Übernahme von Debitoren-/Kreditorenrechnungen in die Accrual Engine
A22: ZACAC_DSITEMS | B22: Nein | C22: Nein | J22: Anzeigen von Abgrenzungsobjekten + kd.eigene Parameter
A23: ZBC_ADDR_CHECK | B23: Nein | C23: Nein | J23: Reparaturprogramm: Prüfen Debitoren auf fehlende Adresse-Einträge in Archivierung
A24: ZBC_AL_REORG_OUT | B24: Nein | C24: Ja | F24: Ja | G24: Nein | J24: Archivelink Reorganisation - Erstellen Löschdatei und Tabelle für's Löschen von Sätzen in den Verknüpfungstabellen
A25: ZBC_AL_REORG_RETURN | B25: Nein | C25: Ja | F25: Ja | G25: Nein | J25: Archivelink Reorganisation - Rückantwort NE-Databridge
A26: ZBC_AL_REORG_VTABS | B26: Nein | C26: Ja | F26: Ja | G26: Nein | J26: Archivelink Reorganisation - Pflege der Verknüpfungstabellen
A27: ZBC_ANONYM_ZQ1 | B27: Nein | C27: Ja | F27: Ja | G27: Nein | J27: Anonymisierungstool in Q Systemen
A28: ZBC_BDCLOG_ALV | B28: Nein | C28: Ja | F28: Ja | G28: Nein | J28: Archivierte BDC Mappenprotokolle anzeigen
A29: ZBC_BDCLOG_ARCHIVE | B29: Nein | C29: Ja | F29: Ja | G29: Nein | J29: BDC Mappenprotokolle archivieren
A30: ZBC_BDCLOG_ARCHIVE_FIX | B30: Nein | C30: Ja | F30: Ja | G30: Nein | J30: BDC Mappenprotokolle archiv Objekte importieren
A31: ZBC_BELEG_VOLUME | B31: Nein | C31: Nein | J31: Ermittlung von Beleganzahl / -wert je Buchungskreis als Basis für Verteilschlüssel SAP Systempreis Verteilung
A32: ZBC_CALL_PROCEDURE | B32: Nein | C32: Nein | J32: Aufruf einer "Stored Procedure" in der Berichtswesendatenbank
A33: ZBC_CHECK_NRIV | B33: Nein | C33: Ja | F33: Ja | G33: Nein | J33: mit diesem Programm können Nummernkreise auf Fehler geprüft werden und freie Intervalle ermittelt werden.
A34: ZBC_COPY_DATASET | B34: Nein | C34: Ja | F34: Ja | G34: Nein | J34: Wird benötigt für ELMO für Dateiaufstellung für Netz HG105C. Es ist eine Kopie von ZFI_COPY_TEXT_DATASET ergänzt mit Archivierungsfunktionalität
A35: ZBC_EVENT_RAISE | B35: Ja | C35: Ja | E35: Ja | J35: Auslösen eines Kundenereignisses
A36: ZBC_EXCELTABUPLOAD | B36: Nein | C36: Nein | J36: Generischer Upload von Excel-Tabellen in R/3-Tabellen
A37: ZBC_F110_JOBCTRL | B37: Nein | C37: Offen | F37: ? | G37: ? | I37: J. Schaut | J37: Zahllauf Folgeverarbeitungssteuerung
A38: ZBC_F110_SPOOL_UPDATE | B38: Nein | C38: Offen | F38: ? | G38: ? | I38: J. Schaut | J38: Update von Spool-Datasets (Zahllaufversion)
A39: ZBC_FILE_DELETE | B39: Ja | C39: Ja | E39: Ja | J39: Dateienlöschung über Report ZBC_FILE_DELETE
A40: ZBC_FILE_EVENT_RAISE | B40: Ja | C40: Ja | E40: Ja | J40: Dateieneventauslösung
A41: ZBC_GET_WORKLOAD_STATISTIC | B41: Nein | C41: Nein | J41: Download Workload Statistics
A42: ZBC_JOB_ABORT | B42: Ja | C42: Ja | E42: Ja | J42: Job Abbrechen wenn eine Liste best. String enthält
A43: ZBC_JOBCONTROL | B43: Nein | C43: Nein
A44: ZBC_LOEVM_DEBI_KREDI | B44: Nein | C44: Nein | J44: Programm zur Pflege der Löschvormerkung für Debitoren und Kreditoren
A45: ZBC_LOEVM_DEBI_KREDI_2 | B45: Nein | C45: Nein | J45: Setzen Löschvormerkung anhand Tage ohne Buchungen
A46: ZBC_LOGO_SWITCH | B46: Nein | C46: Nein | I46: P. Haisch | J46: Logo-Clicks ein/ausschalten -> gehört zu OREA
A47: ZBC_MAESTRO | B47: Nein | C47: Nein | J47: ZBC_MAESTRO
A48: ZBC_NACH_UPDATE_TESTSYSTEM | B48: Nein | C48: Offen | F48: ? | G48: ? | I48: Basis | J48: Update Tabelle NACH im Test-System ("Sofort ausgeben", "Ausgabegerät") -> klären mit Arvato
A49: ZBC_NOTFALLUSERAKTIEVIERUNG | B49: Nein | C49: Nein | J49: Programm zur automatischen Userinaktivierung
A50: ZBC_OREA_COA | B50: Ja | C50: Ja | D50: DEV-105 | E50: Ja | J50: Füllen der COA-Tabellen
A51: ZBC_OREA_COA_NACHVERARBEITUNG | B51: Ja | C51: Ja | E51: Ja | J51: Nachverarbeitung der Freigabehierarchie
A52: ZBC_OREA_COA_TEST | B52: Nein | C52: Nein | I52: P. Haisch | J52: Testutils -> OREA
A53: ZBC_OREA_COA_USER_LOESCHEN | B53: Nein | C53: Offen | F53: ? | G53: ? | I53: A. Gaida / R. Schildberger | J53: Löschen von einzelnen Usern aus der COA
A54: ZBC_OREA_FREIGEBER_TEST | B54: Nein | C54: Ja | D54: DEV-105 | E54: Ja | J54: Test des Freigeberfunktionsbausteins
A55: ZBC_SET_TVARVC | B55: Ja | C55: Ja | E55: Ja | J55: Parameter in TVARVC belegen und updaten
A56: ZBC_SPERR_STAMM_DS | B56: Nein | C56: Nein | J56: Datenschutz: Pflege Berechtigungsgruppe im Stammsatz
A57: ZBC_SPOOL_ARCHIV | B57: Ja | C57: Ja | E57: Ja | J57: Drucklistenarchivierung
A58: ZBC_SPOOL_OUTPUT | B58: Ja | C58: Ja | E58: Ja | J58: Zusätzliches Ausgeben / Senden von Spoollisten
A59: ZBC_SPOOL_PCOUNT | B59: Nein | C59: Ja | F59: Ja | G59: Nein | J59: Ermittlung Seitenanzahl und Ausgabe von Spool-Datasets
A60: ZBC_ST03N | B60: Nein | C60: Nein | J60: Auswertung Systemlast
A61: ZBC_TAB_EXPIMP | B61: Ja | C61: Ja | E61: Ja | J61: ZBC_TAB_EXPIMP Tabellen Exportieren/Importieren
A62: ZBC_TABELLEN_TRANSFER | B62: Nein | C62: Nein | J62: Programm ZBC_TABELLEN_TRANSFER
A63: ZBC_USERINAKTIVIERUNG | B63: Nein | C63: Ja | D63: DEV-084 | E63: Ja | J63: Programm zur automatischen Userinaktivierung
A64: ZBC_VARIANT_LIST | B64: Nein | C64: Ja | F64: Ja | G64: Nein | J64: Reportvarianten-Scanfunktionalität
A65: ZBC_VARIANT_LIST_ALV | B65: Nein | C65: Ja | F65: Ja | G65: Nein | J65: Reportvarianten-Scanfunktionalität
A66: ZBC_ZEMAREP_FRGREORG | B66: Nein | C66: Ja | D66: DEV-084 | E66: Ja | J66: Reorg Tabelle ZBC_ZEMAREP_FRG
A67: ZBC_ZEMAREP_GET | B67: Ja | C67: Ja | D67: DEV-084 | E67: Ja | J67: lesen zemarep
A68: ZBC_ZEMAREP_USER | B68: Ja | C68: Ja | D68: DEV-084 | E68: Ja | J68: ZEMAREP User-Pflege
A69: ZBC_ZEMAREP_USERCHG_REO | B69: Ja | C69: Ja | E69: Ja | J69: Anzeige/Löschen Tabelle ZREP_USERCHG
A70: ZBC_ZEMAREP_USRGUELT | B70: Nein | C70: Ja | D70: DEV-084 | E70: Ja | J70: user gültigkeit prüfen
A71: ZBC_ZRSLG_SERVERS_1692951 | B71: Nein | C71: Nein | J71: Korrekturprogramm Upgrade SNOTE 2164430
A72: ZBC_ZRUTDDLSLDEL_2163340 | B72: Nein | C72: Nein | J72: Korrekturprogramm Upgrade SNOTE 2164430
A73: ZCA_MAIL2 | B73: Nein | C73: Nein | J73: Globale Routinen Luftrettung
A74: ZCA_MAPPCHECK | B74: Ja | C74: Ja | E74: Ja | J74: Mappenstatus
A75: ZCA_TEST_GOS | B75: Nein | C75: Nein | J75: Testprogramm
A76: ZCA_WARTEN | B76: Ja | C76: Ja | E76: Ja | J76: Warten n Minuten (max. 30)
A77: ZCMFIFU1 | B77: Nein | C77: Nein | J77: OSS: 156239 Report Datenaufbau Banksalden
A78: ZCO_ABSTIMMUNG | B78: Nein | C78: Nein | J78: Abstimmung Intercompany
A79: ZCO_ABSTIMMUNG_ARCHIVLINK | B79: Nein | C79: Nein | J79: FI: Archiv_Link_Rechnungsbeleg: FI-Rechnungsdruck
A80: ZCO_ABSTIMMUNG_PRUEFUNG | B80: Nein | C80: Nein | J80: Prüfung der CO/FI-Abstimmung
A81: ZCO_ABZUG_KSTPROJEKT_UMSETZUNG | B81: Nein | C81: Nein | D81: DEV-109 | J81: Programm ZCO_ABZUG_KSTPROJEKT_UMSETZUNG
A82: ZCO_AVM_DATENABZUG | B82: Nein | C82: Nein | D82: DEV-110 | J82: Kostenarten- / Profitcenter-Datenabzug
A83: ZCO_BEWEGUNGSDATEN_ERGRE | B83: Nein | C83: Nein | J83: Initialization und At Selection Screen
A84: ZCO_DATENABZUG_PCA | B84: Nein | C84: Nein
A85: ZCO_DRUCKER_SPOOL | B85: Nein | C85: Nein | D85: DEV-111
A86: ZCO_ERGEBNISRECHNUNG | B86: Nein | C86: Nein | J86: Datenabzug Controlling für die Ergebnisrechnung
A87: ZCO_HIERARCHIEPRUEFUNG | B87: Nein | C87: Nein | J87: Programm ZCO_HIERARCHIEPRUEFUNG
A88: ZCO_IA_ABRECHNUNGSSCHEMA | B88: Nein | C88: Nein | J88: Abrechnungsschema in vorhandenen Aufträgen aktualisieren
A89: ZCO_ILV_AUSWERT | B89: Nein | C89: Nein | J89: Abstimmung SAPCO mit Sachkonten ILV aus SAP-FI
A90: ZCO_ILV_AUTOMABHAK | B90: Nein | C90: Nein | J90: Programm ZCO_ILV_AUTOMABHAK
A91: ZCO_ILV_FI | B91: Nein | C91: Nein | J91: Auswertung FI-Buchungen für ILV
A92: ZCO_ILV_KENNZAHL | B92: Nein | C92: Nein | J92: Programm ZCO_ILV_KENNZAHLEN
A93: ZCO_ILV_KONVERT | B93: Nein | C93: Nein | J93: Konvertierung ILV-Schnittstelle: Alte -> Neue Struktur
A94: ZCO_ILV_LIZENZVERRECHNUNG | B94: Nein | C94: Nein
A95: ZCO_ILV_PCDATEIUEBERNAHME | B95: Nein | C95: Nein | J95: Übernahme der Dateien für die ILV
A96: ZCO_ILV_POSTPROT_AKT | B96: Nein | C96: Nein | J96: Buchungsprotokolltabelle aktualisieren
A97: ZCO_ILV_SAMMLER_LOESCHEN | B97: Nein | C97: Nein | J97: Sammeldateiloeschung
A98: ZCO_ILV_STS | B98: Nein | C98: Nein | J98: Programm ZCO_ILV
A99: ZCO_ILV_VORPROGRAMM | B99: Nein | C99: Nein | J99: Vorprogramm zur ILV
A100: ZCO_KALC_DRUCK | B100: Nein | C100: Nein | J100: KALC FI Belegdaten für den Druck exportieren
...

Sheet Tabelle5
A1: Welle 1 | B1: (Alle)
A2: Welle 2 | B2: (Alle)
A3: Welle 3 ff | B3: (Alle)
B5: Übernahme in S/4 geplant
B6: Ja | C6: Nein | D6: Offen | E6: Gesamtergebnis
A7: Anzahl von Z-Programm R/3 (insgesamt 654) | B7: 265 | C7: 328 | D7: 67 | E7: 660
